单周期多周期CPU设计/Single Cycle Processor/include/Add.v
module Add(Add_a, Add_b, Add_c);
input [31:0] Add_a, Add_b;
output [31:0] Add_c;

assign #0.1 Add_c = Add_a + Add_b;

endmodule

单周期多周期CPU设计/Single Cycle Processor/testbench/Add_tb.v
`timescale 10ns/10ns //第一个是时间单位，第二个是时间精度
`include "../include/Add.v"

module Add_tb;
    wire [31:0] Add_c;
    reg [31:0] a,b;

    initial begin
        $dumpfile("../vcd/Add_tb.vcd");              // 指定记录模拟波形的文件
        $dumpvars(0, Add_tb);          // 指定记录的模块层级                          
        a <= 32'h0011;
        b <= 32'h0001;
        #6000 $finish;  // 6000个单位时间后结束模拟
    end

    always begin
        #20 a = !a;                 // 每20个单位clock取反
    end

    always begin
        #20 b = !b;                 // 每20个单位clock取反
    end

    Add add(.Add_a(a),.Add_b(b),.Add_c(Add_c));

endmodule

单周期多周期CPU设计/Single Cycle Processor/vcd/Add_tb.vcd
$date
	Wed Jan 25 12:59:05 2023
$end
$version
	Icarus Verilog
$end
$timescale
	10ns
$end
$scope module Add_tb $end
$var wire 32 ! Add_c [31:0] $end
$var reg 32 " a [31:0] $end
$var reg 32 # b [31:0] $end
$scope module add $end
$var wire 32 $ Add_a [31:0] $end
$var wire 32 % Add_b [31:0] $end
$var wire 32 & Add_c [31:0] $end
$upscope $end
$upscope $end
$enddefinitions $end
$comment Show the parameter values. $end
$dumpall
$end
#0
$dumpvars
b10010 &
b1 %
b10001 $
b1 #
b10001 "
b10010 !
$end
#20
b0 #
b0 %
b0 !
b0 &
b0 "
b0 $
#40
b1 #
b1 %
b10 !
b10 &
b1 "
b1 $
#60
b0 #
b0 %
b0 !
b0 &
b0 "
b0 $
#80
b1 #
b1 %
b10 !
b10 &
b1 "
b1 $
#100
b0 #
b0 %
b0 !
b0 &
b0 "
b0 $
#120
b1 #
b1 %
b10 !
b10 &
b1 "
b1 $
#140
b0 #
b0 %
b0 !
b0 &
b0 "
b0 $
#160
b1 #
b1 %
b10 !
b10 &
b1 "
b1 $
#180
b0 #
b0 %
b0 !
b0 &
b0 "
b0 $
#200
b1 #
b1 %
b10 !
b10 &
b1 "
b1 $
#220
b0 #
b0 %
b0 !
b0 &
b0 "
b0 $
#240
b1 #
b1 %
b10 !
b10 &
b1 "
b1 $
#260
b0 #
b0 %
b0 !
b0 &
b0 "
b0 $
#280
b1 #
b1 %
b10 !
b10 &
b1 "
b1 $
#300
b0 #
b0 %
b0 !
b0 &
b0 "
b0 $
#320
b1 #
b1 %
b10 !
b10 &
b1 "
b1 $
#340
b0 #
b0 %
b0 !
b0 &
b0 "
b0 $
#360
b1 #
b1 %
b10 !
b10 &
b1 "
b1 $
#380
b0 #
b0 %
b0 !
b0 &
b0 "
b0 $
#400
b1 #
b1 %
b10 !
b10 &
b1 "
b1 $
#420
b0 #
b0 %
b0 !
b0 &
b0 "
b0 $
#440
b1 #
b1 %
b10 !
b10 &
b1 "
b1 $
#460
b0 #
b0 %
b0 !
b0 &
b0 "
b0 $
#480
b1 #
b1 %
b10 !
b10 &
b1 "
b1 $
#500
b0 #
b0 %
b0 !
b0 &
b0 "
b0 $
#520
b1 #
b1 %
b10 !
b10 &
b1 "
b1 $
#540
b0 #
b0 %
b0 !
b0 &
b0 "
b0 $
#560
b1 #
b1 %
b10 !
b10 &
b1 "
b1 $
#580
b0 #
b0 %
b0 !
b0 &
b0 "
b0 $
#600
b1 #
b1 %
b10 !
b10 &
b1 "
b1 $
#620
b0 #
b0 %
b0 !
b0 &
b0 "
b0 $
#640
b1 #
b1 %
b10 !
b10 &
b1 "
b1 $
#660
b0 #
b0 %
b0 !
b0 &
b0 "
b0 $
#680
b1 #
b1 %
b10 !
b10 &
b1 "
b1 $
#700
b0 #
b0 %
b0 !
b0 &
b0 "
b0 $
#720
b1 #
b1 %
b10 !
b10 &
b1 "
b1 $
#740
b0 #
b0 %
b0 !
b0 &
b0 "
b0 $
#760
b1 #
b1 %
b10 !
b10 &
b1 "
b1 $
#780
b0 #
b0 %
b0 !
b0 &
b0 "
b0 $
#800
b1 #
b1 %
b10 !
b10 &
b1 "
b1 $
#820
b0 #
b0 %
b0 !
b0 &
b0 "
b0 $
#840
b1 #
b1 %
b10 !
b10 &
b1 "
b1 $
#860
b0 #
b0 %
b0 !
b0 &
b0 "
b0 $
#880
b1 #
b1 %
b10 !
b10 &
b1 "
b1 $
#900
b0 #
b0 %
b0 !
b0 &
b0 "
b0 $
#920
b1 #
b1 %
b10 !
b10 &
b1 "
b1 $
#940
b0 #
b0 %
b0 !
b0 &
b0 "
b0 $
#960
b1 #
b1 %
b10 !
b10 &
b1 "
b1 $
#980
b0 #
b0 %
b0 !
b0 &
b0 "
b0 $
#1000
b1 #
b1 %
b10 !
b10 &
b1 "
b1 $
#1020
b0 #
b0 %
b0 !
b0 &
b0 "
b0 $
#1040
b1 #
b1 %
b10 !
b10 &
b1 "
b1 $
#1060
b0 #
b0 %
b0 !
b0 &
b0 "
b0 $
#1080
b1 #
b1 %
b10 !
b10 &
b1 "
b1 $
#1100
b0 #
b0 %
b0 !
b0 &
b0 "
b0 $
#1120
b1 #
b1 %
b10 !
b10 &
b1 "
b1 $
#1140
b0 #
b0 %
b0 !
b0 &
b0 "
b0 $
#1160
b1 #
b1 %
b10 !
b10 &
b1 "
b1 $
#1180
b0 #
b0 %
b0 !
b0 &
b0 "
b0 $
#1200
b1 #
b1 %
b10 !
b10 &
b1 "
b1 $
#1220
b0 #
b0 %
b0 !
b0 &
b0 "
b0 $
#1240
b1 #
b1 %
b10 !
b10 &
b1 "
b1 $
#1260
b0 #
b0 %
b0 !
b0 &
b0 "
b0 $
#1280
b1 #
b1 %
b10 !
b10 &
b1 "
b1 $
#1300
b0 #
b0 %
b0 !
b0 &
b0 "
b0 $
#1320
b1 #
b1 %
b10 !
b10 &
b1 "
b1 $
#1340
b0 #
b0 %
b0 !
b0 &
b0 "
b0 $
#1360
b1 #
b1 %
b10 !
b10 &
b1 "
b1 $
#1380
b0 #
b0 %
b0 !
b0 &
b0 "
b0 $
#1400
b1 #
b1 %
b10 !
b10 &
b1 "
b1 $
#1420
b0 #
b0 %
b0 !
b0 &
b0 "
b0 $
#1440
b1 #
b1 %
b10 !
b10 &
b1 "
b1 $
#1460
b0 #
b0 %
b0 !
b0 &
b0 "
b0 $
#1480
b1 #
b1 %
b10 !
b10 &
b1 "
b1 $
#1500
b0 #
b0 %
b0 !
b0 &
b0 "
b0 $
#1520
b1 #
b1 %
b10 !
b10 &
b1 "
b1 $
#1540
b0 #
b0 %
b0 !
b0 &
b0 "
b0 $
#1560
b1 #
b1 %
b10 !
b10 &
b1 "
b1 $
#1580
b0 #
b0 %
b0 !
b0 &
b0 "
b0 $
#1600
b1 #
b1 %
b10 !
b10 &
b1 "
b1 $
#1620
b0 #
b0 %
b0 !
b0 &
b0 "
b0 $
#1640
b1 #
b1 %
b10 !
b10 &
b1 "
b1 $
#1660
b0 #
b0 %
b0 !
b0 &
b0 "
b0 $
#1680
b1 #
b1 %
b10 !
b10 &
b1 "
b1 $
#1700
b0 #
b0 %
b0 !
b0 &
b0 "
b0 $
#1720
b1 #
b1 %
b10 !
b10 &
b1 "
b1 $
#1740
b0 #
b0 %
b0 !
b0 &
b0 "
b0 $
#1760
b1 #
b1 %
b10 !
b10 &
b1 "
b1 $
#1780
b0 #
b0 %
b0 !
b0 &
b0 "
b0 $
#1800
b1 #
b1 %
b10 !
b10 &
b1 "
b1 $
#1820
b0 #
b0 %
b0 !
b0 &
b0 "
b0 $
#1840
b1 #
b1 %
b10 !
b10 &
b1 "
b1 $
#1860
b0 #
b0 %
b0 !
b0 &
b0 "
b0 $
#1880
b1 #
b1 %
b10 !
b10 &
b1 "
b1 $
#1900
b0 #
b0 %
b0 !
b0 &
b0 "
b0 $
#1920
b1 #
b1 %
b10 !
b10 &
b1 "
b1 $
#1940
b0 #
b0 %
b0 !
b0 &
b0 "
b0 $
#1960
b1 #
b1 %
b10 !
b10 &
b1 "
b1 $
#1980
b0 #
b0 %
b0 !
b0 &
b0 "
b0 $
#2000
b1 #
b1 %
b10 !
b10 &
b1 "
b1 $
#2020
b0 #
b0 %
b0 !
b0 &
b0 "
b0 $
#2040
b1 #
b1 %
b10 !
b10 &
b1 "
b1 $
#2060
b0 #
b0 %
b0 !
b0 &
b0 "
b0 $
#2080
b1 #
b1 %
b10 !
b10 &
b1 "
b1 $
#2100
b0 #
b0 %
b0 !
b0 &
b0 "
b0 $
#2120
b1 #
b1 %
b10 !
b10 &
b1 "
b1 $
#2140
b0 #
b0 %
b0 !
b0 &
b0 "
b0 $
#2160
b1 #
b1 %
b10 !
b10 &
b1 "
b1 $
#2180
b0 #
b0 %
b0 !
b0 &
b0 "
b0 $
#2200
b1 #
b1 %
b10 !
b10 &
b1 "
b1 $
#2220
b0 #
b0 %
b0 !
b0 &
b0 "
b0 $
#2240
b1 #
b1 %
b10 !
b10 &
b1 "
b1 $
#2260
b0 #
b0 %
b0 !
b0 &
b0 "
b0 $
#2280
b1 #
b1 %
b10 !
b10 &
b1 "
b1 $
#2300
b0 #
b0 %
b0 !
b0 &
b0 "
b0 $
#2320
b1 #
b1 %
b10 !
b10 &
b1 "
b1 $
#2340
b0 #
b0 %
b0 !
b0 &
b0 "
b0 $
#2360
b1 #
b1 %
b10 !
b10 &
b1 "
b1 $
#2380
b0 #
b0 %
b0 !
b0 &
b0 "
b0 $
#2400
b1 #
b1 %
b10 !
b10 &
b1 "
b1 $
#2420
b0 #
b0 %
b0 !
b0 &
b0 "
b0 $
#2440
b1 #
b1 %
b10 !
b10 &
b1 "
b1 $
#2460
b0 #
b0 %
b0 !
b0 &
b0 "
b0 $
#2480
b1 #
b1 %
b10 !
b10 &
b1 "
b1 $
#2500
b0 #
b0 %
b0 !
b0 &
b0 "
b0 $
#2520
b1 #
b1 %
b10 !
b10 &
b1 "
b1 $
#2540
b0 #
b0 %
b0 !
b0 &
b0 "
b0 $
#2560
b1 #
b1 %
b10 !
b10 &
b1 "
b1 $
#2580
b0 #
b0 %
b0 !
b0 &
b0 "
b0 $
#2600
b1 #
b1 %
b10 !
b10 &
b1 "
b1 $
#2620
b0 #
b0 %
b0 !
b0 &
b0 "
b0 $
#2640
b1 #
b1 %
b10 !
b10 &
b1 "
b1 $
#2660
b0 #
b0 %
b0 !
b0 &
b0 "
b0 $
#2680
b1 #
b1 %
b10 !
b10 &
b1 "
b1 $
#2700
b0 #
b0 %
b0 !
b0 &
b0 "
b0 $
#2720
b1 #
b1 %
b10 !
b10 &
b1 "
b1 $
#2740
b0 #
b0 %
b0 !
b0 &
b0 "
b0 $
#2760
b1 #
b1 %
b10 !
b10 &
b1 "
b1 $
#2780
b0 #
b0 %
b0 !
b0 &
b0 "
b0 $
#2800
b1 #
b1 %
b10 !
b10 &
b1 "
b1 $
#2820
b0 #
b0 %
b0 !
b0 &
b0 "
b0 $
#2840
b1 #
b1 %
b10 !
b10 &
b1 "
b1 $
#2860
b0 #
b0 %
b0 !
b0 &
b0 "
b0 $
#2880
b1 #
b1 %
b10 !
b10 &
b1 "
b1 $
#2900
b0 #
b0 %
b0 !
b0 &
b0 "
b0 $
#2920
b1 #
b1 %
b10 !
b10 &
b1 "
b1 $
#2940
b0 #
b0 %
b0 !
b0 &
b0 "
b0 $
#2960
b1 #
b1 %
b10 !
b10 &
b1 "
b1 $
#2980
b0 #
b0 %
b0 !
b0 &
b0 "
b0 $
#3000
b1 #
b1 %
b10 !
b10 &
b1 "
b1 $
#3020
b0 #
b0 %
b0 !
b0 &
b0 "
b0 $
#3040
b1 #
b1 %
b10 !
b10 &
b1 "
b1 $
#3060
b0 #
b0 %
b0 !
b0 &
b0 "
b0 $
#3080
b1 #
b1 %
b10 !
b10 &
b1 "
b1 $
#3100
b0 #
b0 %
b0 !
b0 &
b0 "
b0 $
#3120
b1 #
b1 %
b10 !
b10 &
b1 "
b1 $
#3140
b0 #
b0 %
b0 !
b0 &
b0 "
b0 $
#3160
b1 #
b1 %
b10 !
b10 &
b1 "
b1 $
#3180
b0 #
b0 %
b0 !
b0 &
b0 "
b0 $
#3200
b1 #
b1 %
b10 !
b10 &
b1 "
b1 $
#3220
b0 #
b0 %
b0 !
b0 &
b0 "
b0 $
#3240
b1 #
b1 %
b10 !
b10 &
b1 "
b1 $
#3260
b0 #
b0 %
b0 !
b0 &
b0 "
b0 $
#3280
b1 #
b1 %
b10 !
b10 &
b1 "
b1 $
#3300
b0 #
b0 %
b0 !
b0 &
b0 "
b0 $
#3320
b1 #
b1 %
b10 !
b10 &
b1 "
b1 $
#3340
b0 #
b0 %
b0 !
b0 &
b0 "
b0 $
#3360
b1 #
b1 %
b10 !
b10 &
b1 "
b1 $
#3380
b0 #
b0 %
b0 !
b0 &
b0 "
b0 $
#3400
b1 #
b1 %
b10 !
b10 &
b1 "
b1 $
#3420
b0 #
b0 %
b0 !
b0 &
b0 "
b0 $
#3440
b1 #
b1 %
b10 !
b10 &
b1 "
b1 $
#3460
b0 #
b0 %
b0 !
b0 &
b0 "
b0 $
#3480
b1 #
b1 %
b10 !
b10 &
b1 "
b1 $
#3500
b0 #
b0 %
b0 !
b0 &
b0 "
b0 $
#3520
b1 #
b1 %
b10 !
b10 &
b1 "
b1 $
#3540
b0 #
b0 %
b0 !
b0 &
b0 "
b0 $
#3560
b1 #
b1 %
b10 !
b10 &
b1 "
b1 $
#3580
b0 #
b0 %
b0 !
b0 &
b0 "
b0 $
#3600
b1 #
b1 %
b10 !
b10 &
b1 "
b1 $
#3620
b0 #
b0 %
b0 !
b0 &
b0 "
b0 $
#3640
b1 #
b1 %
b10 !
b10 &
b1 "
b1 $
#3660
b0 #
b0 %
b0 !
b0 &
b0 "
b0 $
#3680
b1 #
b1 %
b10 !
b10 &
b1 "
b1 $
#3700
b0 #
b0 %
b0 !
b0 &
b0 "
b0 $
#3720
b1 #
b1 %
b10 !
b10 &
b1 "
b1 $
#3740
b0 #
b0 %
b0 !
b0 &
b0 "
b0 $
#3760
b1 #
b1 %
b10 !
b10 &
b1 "
b1 $
#3780
b0 #
b0 %
b0 !
b0 &
b0 "
b0 $
#3800
b1 #
b1 %
b10 !
b10 &
b1 "
b1 $
#3820
b0 #
b0 %
b0 !
b0 &
b0 "
b0 $
#3840
b1 #
b1 %
b10 !
b10 &
b1 "
b1 $
#3860
b0 #
b0 %
b0 !
b0 &
b0 "
b0 $
#3880
b1 #
b1 %
b10 !
b10 &
b1 "
b1 $
#3900
b0 #
b0 %
b0 !
b0 &
b0 "
b0 $
#3920
b1 #
b1 %
b10 !
b10 &
b1 "
b1 $
#3940
b0 #
b0 %
b0 !
b0 &
b0 "
b0 $
#3960
b1 #
b1 %
b10 !
b10 &
b1 "
b1 $
#3980
b0 #
b0 %
b0 !
b0 &
b0 "
b0 $
#4000
b1 #
b1 %
b10 !
b10 &
b1 "
b1 $
#4020
b0 #
b0 %
b0 !
b0 &
b0 "
b0 $
#4040
b1 #
b1 %
b10 !
b10 &
b1 "
b1 $
#4060
b0 #
b0 %
b0 !
b0 &
b0 "
b0 $
#4080
b1 #
b1 %
b10 !
b10 &
b1 "
b1 $
#4100
b0 #
b0 %
b0 !
b0 &
b0 "
b0 $
#4120
b1 #
b1 %
b10 !
b10 &
b1 "
b1 $
#4140
b0 #
b0 %
b0 !
b0 &
b0 "
b0 $
#4160
b1 #
b1 %
b10 !
b10 &
b1 "
b1 $
#4180
b0 #
b0 %
b0 !
b0 &
b0 "
b0 $
#4200
b1 #
b1 %
b10 !
b10 &
b1 "
b1 $
#4220
b0 #
b0 %
b0 !
b0 &
b0 "
b0 $
#4240
b1 #
b1 %
b10 !
b10 &
b1 "
b1 $
#4260
b0 #
b0 %
b0 !
b0 &
b0 "
b0 $
#4280
b1 #
b1 %
b10 !
b10 &
b1 "
b1 $
#4300
b0 #
b0 %
b0 !
b0 &
b0 "
b0 $
#4320
b1 #
b1 %
b10 !
b10 &
b1 "
b1 $
#4340
b0 #
b0 %
b0 !
b0 &
b0 "
b0 $
#4360
b1 #
b1 %
b10 !
b10 &
b1 "
b1 $
#4380
b0 #
b0 %
b0 !
b0 &
b0 "
b0 $
#4400
b1 #
b1 %
b10 !
b10 &
b1 "
b1 $
#4420
b0 #
b0 %
b0 !
b0 &
b0 "
b0 $
#4440
b1 #
b1 %
b10 !
b10 &
b1 "
b1 $
#4460
b0 #
b0 %
b0 !
b0 &
b0 "
b0 $
#4480
b1 #
b1 %
b10 !
b10 &
b1 "
b1 $
#4500
b0 #
b0 %
b0 !
b0 &
b0 "
b0 $
#4520
b1 #
b1 %
b10 !
b10 &
b1 "
b1 $
#4540
b0 #
b0 %
b0 !
b0 &
b0 "
b0 $
#4560
b1 #
b1 %
b10 !
b10 &
b1 "
b1 $
#4580
b0 #
b0 %
b0 !
b0 &
b0 "
b0 $
#4600
b1 #
b1 %
b10 !
b10 &
b1 "
b1 $
#4620
b0 #
b0 %
b0 !
b0 &
b0 "
b0 $
#4640
b1 #
b1 %
b10 !
b10 &
b1 "
b1 $
#4660
b0 #
b0 %
b0 !
b0 &
b0 "
b0 $
#4680
b1 #
b1 %
b10 !
b10 &
b1 "
b1 $
#4700
b0 #
b0 %
b0 !
b0 &
b0 "
b0 $
#4720
b1 #
b1 %
b10 !
b10 &
b1 "
b1 $
#4740
b0 #
b0 %
b0 !
b0 &
b0 "
b0 $
#4760
b1 #
b1 %
b10 !
b10 &
b1 "
b1 $
#4780
b0 #
b0 %
b0 !
b0 &
b0 "
b0 $
#4800
b1 #
b1 %
b10 !
b10 &
b1 "
b1 $
#4820
b0 #
b0 %
b0 !
b0 &
b0 "
b0 $
#4840
b1 #
b1 %
b10 !
b10 &
b1 "
b1 $
#4860
b0 #
b0 %
b0 !
b0 &
b0 "
b0 $
#4880
b1 #
b1 %
b10 !
b10 &
b1 "
b1 $
#4900
b0 #
b0 %
b0 !
b0 &
b0 "
b0 $
#4920
b1 #
b1 %
b10 !
b10 &
b1 "
b1 $
#4940
b0 #
b0 %
b0 !
b0 &
b0 "
b0 $
#4960
b1 #
b1 %
b10 !
b10 &
b1 "
b1 $
#4980
b0 #
b0 %
b0 !
b0 &
b0 "
b0 $
#5000
b1 #
b1 %
b10 !
b10 &
b1 "
b1 $
#5020
b0 #
b0 %
b0 !
b0 &
b0 "
b0 $
#5040
b1 #
b1 %
b10 !
b10 &
b1 "
b1 $
#5060
b0 #
b0 %
b0 !
b0 &
b0 "
b0 $
#5080
b1 #
b1 %
b10 !
b10 &
b1 "
b1 $
#5100
b0 #
b0 %
b0 !
b0 &
b0 "
b0 $
#5120
b1 #
b1 %
b10 !
b10 &
b1 "
b1 $
#5140
b0 #
b0 %
b0 !
b0 &
b0 "
b0 $
#5160
b1 #
b1 %
b10 !
b10 &
b1 "
b1 $
#5180
b0 #
b0 %
b0 !
b0 &
b0 "
b0 $
#5200
b1 #
b1 %
b10 !
b10 &
b1 "
b1 $
#5220
b0 #
b0 %
b0 !
b0 &
b0 "
b0 $
#5240
b1 #
b1 %
b10 !
b10 &
b1 "
b1 $
#5260
b0 #
b0 %
b0 !
b0 &
b0 "
b0 $
#5280
b1 #
b1 %
b10 !
b10 &
b1 "
b1 $
#5300
b0 #
b0 %
b0 !
b0 &
b0 "
b0 $
#5320
b1 #
b1 %
b10 !
b10 &
b1 "
b1 $
#5340
b0 #
b0 %
b0 !
b0 &
b0 "
b0 $
#5360
b1 #
b1 %
b10 !
b10 &
b1 "
b1 $
#5380
b0 #
b0 %
b0 !
b0 &
b0 "
b0 $
#5400
b1 #
b1 %
b10 !
b10 &
b1 "
b1 $
#5420
b0 #
b0 %
b0 !
b0 &
b0 "
b0 $
#5440
b1 #
b1 %
b10 !
b10 &
b1 "
b1 $
#5460
b0 #
b0 %
b0 !
b0 &
b0 "
b0 $
#5480
b1 #
b1 %
b10 !
b10 &
b1 "
b1 $
#5500
b0 #
b0 %
b0 !
b0 &
b0 "
b0 $
#5520
b1 #
b1 %
b10 !
b10 &
b1 "
b1 $
#5540
b0 #
b0 %
b0 !
b0 &
b0 "
b0 $
#5560
b1 #
b1 %
b10 !
b10 &
b1 "
b1 $
#5580
b0 #
b0 %
b0 !
b0 &
b0 "
b0 $
#5600
b1 #
b1 %
b10 !
b10 &
b1 "
b1 $
#5620
b0 #
b0 %
b0 !
b0 &
b0 "
b0 $
#5640
b1 #
b1 %
b10 !
b10 &
b1 "
b1 $
#5660
b0 #
b0 %
b0 !
b0 &
b0 "
b0 $
#5680
b1 #
b1 %
b10 !
b10 &
b1 "
b1 $
#5700
b0 #
b0 %
b0 !
b0 &
b0 "
b0 $
#5720
b1 #
b1 %
b10 !
b10 &
b1 "
b1 $
#5740
b0 #
b0 %
b0 !
b0 &
b0 "
b0 $
#5760
b1 #
b1 %
b10 !
b10 &
b1 "
b1 $
#5780
b0 #
b0 %
b0 !
b0 &
b0 "
b0 $
#5800
b1 #
b1 %
b10 !
b10 &
b1 "
b1 $
#5820
b0 #
b0 %
b0 !
b0 &
b0 "
b0 $
#5840
b1 #
b1 %
b10 !
b10 &
b1 "
b1 $
#5860
b0 #
b0 %
b0 !
b0 &
b0 "
b0 $
#5880
b1 #
b1 %
b10 !
b10 &
b1 "
b1 $
#5900
b0 #
b0 %
b0 !
b0 &
b0 "
b0 $
#5920
b1 #
b1 %
b10 !
b10 &
b1 "
b1 $
#5940
b0 #
b0 %
b0 !
b0 &
b0 "
b0 $
#5960
b1 #
b1 %
b10 !
b10 &
b1 "
b1 $
#5980
b0 #
b0 %
b0 !
b0 &
b0 "
b0 $
#6000
b1 #
b1 %
b10 !
b10 &
b1 "
b1 $
