单周期多周期CPU设计/Multi Cycle Processor/include/mux2.v
//parameter指定输入的位数
//多路选择器产生选通规定有0.1个时间单位的延时
module mux2(in0,in1,out,addr);
parameter width = 31;
input [width:0] in0, in1;
input addr;
output [width:0] out;

assign #0.1 out = addr? in1 : in0;

endmodule

单周期多周期CPU设计/Single Cycle Processor/include/SigExt.v
module SigExt(in,out);
input wire signed [15:0] in;
output wire signed [31:0] out;

assign #0.1 out = {{16{in[15]}}, in};


endmodule

单周期多周期CPU设计/Single Cycle Processor/include/ALU.v
module ALU(ALU_a,ALU_b,ALUCtrl,Zero,O,ALU_c);
input [31:0] ALU_a,ALU_b;
input [2:0] ALUCtrl;
output reg [31:0] ALU_c;
output reg Zero;
output reg O;

parameter ALU_pause=0,
          AND=3'b000,//
          OR=3'b001,//
          ADD=3'b100,//
          SUB=3'b110,//
          NOR=3'b011,//
          ADDU=3'b101;

always @(ALU_a or ALU_b or ALUCtrl) begin
    #0.1
    case(ALUCtrl)
        AND: ALU_c <= ALU_a & ALU_b;
        OR: ALU_c <= ALU_a | ALU_b;
        ADD: {O,ALU_c} <= ALU_a + ALU_b;
        SUB: {O,ALU_c} <= ALU_a - ALU_b;
        NOR: ALU_c <= ~ (ALU_a | ALU_b);
        ADDU: ALU_c <= ALU_a + ALU_b;
    endcase
end

always @(ALU_c) begin
    if (ALU_c == 0)
        Zero <= 1;
    else 
        Zero <= 0;
end

endmodule

单周期多周期CPU设计/Single Cycle Processor/include/Add.v
module Add(Add_a, Add_b, Add_c);
input [31:0] Add_a, Add_b;
output [31:0] Add_c;

assign #0.1 Add_c = Add_a + Add_b;

endmodule

单周期多周期CPU设计/Single Cycle Processor/include/RF.v
//只有写使能，没有输出使能
//可以同时读两个寄存器，写一个寄存器
//寄存器堆RF有32个32位寄存器
//任何时候都可以读，时钟上跳沿来写数据
module RF(R_Reg1,R_Reg2,W_Reg,W_data,R_data1,R_data2,clk,RegWr);
input [4:0] R_Reg1, R_Reg2, W_Reg;
input [31:0] W_data;
input clk, RegWr;
output [31:0] R_data1, R_data2;

reg [31:0] RF [31:0];//注意第二个是元素个数不是位宽

assign #0.1 R_data1 = RF[R_Reg1];
assign #0.1 R_data2 = RF[R_Reg2];

always @(posedge clk ) begin
    if(RegWr)
        #0.1 RF[W_Reg] <= W_data;
end

endmodule

单周期多周期CPU设计/Single Cycle Processor/include/RAM.v
//有写使能和输出使能，可以同时读一个和写一个
//输出和写入有1个时间单位的延时
module RAM(R_data,W_data,Addr,MemWr,MemRd);
input [31:0] Addr,W_data;
input MemWr, MemRd;
output [31:0] R_data;

reg [7:0] mem [16'hffff:0]; //size:2^16 x Byte =64KB

//输出的状态
assign #1 R_data = MemRd? {mem[Addr+3],mem[Addr+2],mem[Addr+1],mem[Addr]} : 32'hzzzz; //连续赋值assign始终处于活动状态

//写入的状态
always @(posedge MemWr ) begin
    #1 
    mem[Addr+3] <= W_data[31:24];
    mem[Addr+2] <= W_data[23:16];
    mem[Addr+1] <= W_data[15:8];
    mem[Addr] <= W_data[7:0];
end

endmodule

单周期多周期CPU设计/Single Cycle Processor/include/ROM.v
//只读寄存器
module ROM(R_data,Addr);
input [31:0] Addr;
output [31:0] R_data;

reg [7:0] mem [16'hffff:0]; //size:2^16 x Byte =64KB

//输出
assign #1 R_data = {mem[Addr+3],mem[Addr+2],mem[Addr+1],mem[Addr]};//小端模式，高字节高地址

endmodule

单周期多周期CPU设计/Single Cycle Processor/include/PC.v
//写数据设置有0.1个时间单位的延迟
//读数据输出类型为reg，一直可读
module PC(clk,data,Q);
input clk;
// input RegOe;
input [31:0] data;
output reg [31:0] Q;

always @(posedge clk ) begin
    #0.1
    Q <=  data;
end

endmodule

单周期多周期CPU设计/Single Cycle Processor/include/ALU_CU.v
module ALU_CU (ALUOp,func,ALUCtrl);
input [5:0] func;
input [1:0] ALUOp;
output reg [2:0] ALUCtrl;

always @(func or ALUOp) begin
    #0.1
    casex(ALUOp) 
        2'b00: ALUCtrl <= 100;
        2'b01: ALUCtrl <= 110;
        2'b1x: begin
          case (func)
            6'b100000: ALUCtrl <= 100;
            6'b100001: ALUCtrl <= 101;
            6'b100010: ALUCtrl <= 110;
            6'b100100: ALUCtrl <= 000;
            6'b100101: ALUCtrl <= 001;
            6'b101010: ALUCtrl <= 011;
          endcase
        end
    endcase
end
endmodule

单周期多周期CPU设计/Single Cycle Processor/include/CU.v
//单周期cpu一次就产生所有需要的选通信号
//在一个周期内完成所有操作
//由于逻辑结构较为简单，采用组合逻辑的方法实现
module CU(OP_Code, RegDst, RegWr, ALUSrc, MemRd, MemWr, MemtoReg, Branch, Jump, ALUOp);
input [5:0] OP_Code;
output reg RegDst, RegWr, ALUSrc, MemRd, MemWr, MemtoReg, Branch, Jump;
output reg [1:0] ALUOp;

parameter R_type = 6'b000000,
          lw = 6'b100011,
          sw = 6'b101011,
          beq = 6'b000100,
          j = 6'b000010,
          addiu = 6'b001001;
always @(OP_Code) begin
    #0.1
    case(OP_Code)
        R_type: {RegDst, RegWr, ALUSrc, MemRd, MemWr, MemtoReg, Branch, Jump, ALUOp} <= 10'b1100000010;
        lw: {RegDst, RegWr, ALUSrc, MemRd, MemWr, MemtoReg, Branch, Jump, ALUOp} <= 10'b0111010000;
        sw: {RegDst, RegWr, ALUSrc, MemRd, MemWr, MemtoReg, Branch, Jump, ALUOp} <= 10'bx0101x0000;
        beq: {RegDst, RegWr, ALUSrc, MemRd, MemWr, MemtoReg, Branch, Jump, ALUOp} <= 10'bx0000x1001;
        j: {RegDst, RegWr, ALUSrc, MemRd, MemWr, MemtoReg, Branch, Jump, ALUOp} <= 10'bx0x00x01xx;
        addiu:{RegDst, RegWr, ALUSrc, MemRd, MemWr, MemtoReg, Branch, Jump, ALUOp} <= 10'b0110000000;
    endcase
end
endmodule

单周期多周期CPU设计/Single Cycle Processor/include/CPU.v
//这里包含cpu的所有连线
//指令寄存器和数据寄存器也在此连线了

// `include "ALU_CU.v"
// `include "ALU.v"
// `include "CU.v"
// `include "Add.v"
// `include "mux2.v"
// `include "PC.v"
// `include "RAM.v"
// `include "ROM.v"
// `include "RF.v"
// `include "SigExt.v"
module CPU(clk);
input clk;

//控制信号线
wire RegDst, RegWr, ALUSrc, MemRd, MemWr, MemtoReg, Branch, Jump;
wire [1:0] ALUOp;
wire [2:0] ALUCtrl;
//RF上接的线,图中用蓝色标识
wire [31:0] RF_W_data, RF_data1, RF_data2;
wire [4:0] RF_W_Reg;

//指令存储器的输出线，图中用绿色标识
wire [31:0] Inst;
//数据存储器的输出线，图中用橙色标识
wire [31:0] Data;

//PC上连的线,图中用粉色标识
wire [31:0] pc_in, pc_out;
//ALU上连的线，图上用黄色标识
wire [31:0] ALU_c, ALU_b;
wire Zero, O;

//其他较为零散的连线,图中用淡紫色标识
wire [31:0] SigExt_out;//移位器的输出线
wire [31:0] Add_1_c;//add1的输出线
wire [31:0] Add_2_c;//add2的输出线
wire [31:0] mux_4_out;//4号多路选择器的输出线

//控制单元连线
CU MCU (.OP_Code(Inst[31:26]), .RegDst(RegDst), .RegWr(RegWr), .ALUSrc(ALUSrc), .MemRd(MemRd), .MemWr(MemWr), .MemtoReg(MemtoReg), .Branch(Branch), .Jump(Jump), .ALUOp(ALUOp));
ALU_CU alu_cu (.ALUOp(ALUOp), .func(Inst[5:0]), .ALUCtrl(ALUCtrl));

//寄存器和存储器连线
PC pc (.clk(clk), .data(pc_in), .Q(pc_out));
ROM Inst_mem (.R_data(Inst), .Addr(pc_out));
RAM Data_mem (.R_data(Data), .W_data(RF_data2), .Addr(ALU_c), .MemWr(MemWr), .MemRd(MemRd));
RF RegFile (.R_Reg1(Inst[25:21]), .R_Reg2(Inst[20:16]), .W_Reg(RF_W_Reg), .W_data(RF_W_data), .R_data1(RF_data1), .R_data2(RF_data2), .clk(clk), .RegWr(RegWr));

//运算单元连线
Add Add_1 (.Add_a(32'h0004), .Add_b(pc_out), .Add_c(Add_1_c));
Add Add_2 (.Add_a(Add_1_c), .Add_b(SigExt_out<<2), .Add_c(Add_2_c));
ALU alu (.ALU_a(RF_data1), .ALU_b(ALU_b), .ALUCtrl(ALUCtrl), .Zero(Zero), .O(O), .ALU_c(ALU_c));
SigExt sigext (.in(Inst[15:0]), .out(SigExt_out));

//多路选择器连线
mux2 #(4) mux_1 (.in0(Inst[20:16]), .in1(Inst[15:11]), .out(RF_W_Reg), .addr(RegDst));
mux2 mux_2 (.in0(RF_data2), .in1(SigExt_out), .out(ALU_b), .addr(ALUSrc));
mux2 mux_3 (.in0(ALU_c), .in1(Data), .out(RF_W_data), .addr(MemtoReg));
mux2 mux_4 (.in0(Add_1_c), .in1(Add_2_c), .out(mux_4_out), .addr(Zero & Branch));
mux2 mux_5 (.in0(mux_4_out), .in1({Add_1_c[31:28],Inst[25:0],2'b00}), .out(pc_in), .addr(Jump));

endmodule

单周期多周期CPU设计/Single Cycle Processor/testbench/CPU_run1_tb.v
`timescale 10ns/1ns
`include "../include/CPU.v"
`include "../include/ALU_CU.v"
`include "../include/ALU.v"
`include "../include/CU.v"
`include "../include/Add.v"
`include "../include/mux2.v"
`include "../include/PC.v"
`include "../include/RAM.v"
`include "../include/ROM.v"
`include "../include/RF.v"
`include "../include/SigExt.v"

module CPU_run1_tb;
    reg clk;
    parameter clk_period = 10;

    initial begin
        $dumpfile("../vcd/CPU_run1_tb.vcd");             
        $dumpvars(0, CPU_run1_tb); 
        $readmemh("../file/run1.txt",cpu.Inst_mem.mem);//设置指令存储器初值
        $readmemh("../file/run1_RF.txt",cpu.RegFile.RF);//设置RF初值,$0寄存器的值恒为0
        
        clk <= 1 ;
        #0.2 cpu.pc.Q <= 32'h0;

        // #10
        // $display("%h",cpu.RegFile.RF[8]);
        // #10
        // $display("%h",cpu.RegFile.RF[9]);

        #6000 $finish; 
    end

    always #(clk_period/2) clk = ~clk;

    CPU cpu(.clk(clk));

endmodule

单周期多周期CPU设计/Single Cycle Processor/vcd/CPU_run1_tb.vcd
$date
	Mon Feb 27 23:49:16 2023
$end
$version
	Icarus Verilog
$end
$timescale
	1ns
$end
$scope module CPU_run1_tb $end
$var parameter 32 ! clk_period $end
$var reg 1 " clk $end
$scope module cpu $end
$var wire 1 " clk $end
$var wire 32 # pc_out [31:0] $end
$var wire 32 $ pc_in [31:0] $end
$var wire 32 % mux_4_out [31:0] $end
$var wire 1 & Zero $end
$var wire 32 ' SigExt_out [31:0] $end
$var wire 1 ( RegWr $end
$var wire 1 ) RegDst $end
$var wire 32 * RF_data2 [31:0] $end
$var wire 32 + RF_data1 [31:0] $end
$var wire 32 , RF_W_data [31:0] $end
$var wire 5 - RF_W_Reg [4:0] $end
$var wire 1 . O $end
$var wire 1 / MemtoReg $end
$var wire 1 0 MemWr $end
$var wire 1 1 MemRd $end
$var wire 1 2 Jump $end
$var wire 32 3 Inst [31:0] $end
$var wire 32 4 Data [31:0] $end
$var wire 1 5 Branch $end
$var wire 32 6 Add_2_c [31:0] $end
$var wire 32 7 Add_1_c [31:0] $end
$var wire 32 8 ALU_c [31:0] $end
$var wire 32 9 ALU_b [31:0] $end
$var wire 1 : ALUSrc $end
$var wire 2 ; ALUOp [1:0] $end
$var wire 3 < ALUCtrl [2:0] $end
$scope module Add_1 $end
$var wire 32 = Add_a [31:0] $end
$var wire 32 > Add_c [31:0] $end
$var wire 32 ? Add_b [31:0] $end
$upscope $end
$scope module Add_2 $end
$var wire 32 @ Add_a [31:0] $end
$var wire 32 A Add_b [31:0] $end
$var wire 32 B Add_c [31:0] $end
$upscope $end
$scope module Data_mem $end
$var wire 32 C W_data [31:0] $end
$var wire 32 D R_data [31:0] $end
$var wire 1 0 MemWr $end
$var wire 1 1 MemRd $end
$var wire 32 E Addr [31:0] $end
$upscope $end
$scope module Inst_mem $end
$var wire 32 F R_data [31:0] $end
$var wire 32 G Addr [31:0] $end
$upscope $end
$scope module MCU $end
$var wire 6 H OP_Code [5:0] $end
$var parameter 6 I R_type $end
$var parameter 6 J addiu $end
$var parameter 6 K beq $end
$var parameter 6 L j $end
$var parameter 6 M lw $end
$var parameter 6 N sw $end
$var reg 2 O ALUOp [1:0] $end
$var reg 1 : ALUSrc $end
$var reg 1 5 Branch $end
$var reg 1 2 Jump $end
$var reg 1 1 MemRd $end
$var reg 1 0 MemWr $end
$var reg 1 / MemtoReg $end
$var reg 1 ) RegDst $end
$var reg 1 ( RegWr $end
$upscope $end
$scope module RegFile $end
$var wire 5 P R_Reg1 [4:0] $end
$var wire 5 Q R_Reg2 [4:0] $end
$var wire 32 R R_data1 [31:0] $end
$var wire 32 S R_data2 [31:0] $end
$var wire 1 ( RegWr $end
$var wire 1 " clk $end
$var wire 32 T W_data [31:0] $end
$var wire 5 U W_Reg [4:0] $end
$upscope $end
$scope module alu $end
$var wire 32 V ALU_a [31:0] $end
$var wire 32 W ALU_b [31:0] $end
$var wire 3 X ALUCtrl [2:0] $end
$var parameter 3 Y ADD $end
$var parameter 3 Z ADDU $end
$var parameter 32 [ ALU_pause $end
$var parameter 3 \ AND $end
$var parameter 3 ] NOR $end
$var parameter 3 ^ OR $end
$var parameter 3 _ SUB $end
$var reg 32 ` ALU_c [31:0] $end
$var reg 1 . O $end
$var reg 1 & Zero $end
$upscope $end
$scope module alu_cu $end
$var wire 2 a ALUOp [1:0] $end
$var wire 6 b func [5:0] $end
$var reg 3 c ALUCtrl [2:0] $end
$upscope $end
$scope module mux_1 $end
$var wire 1 ) addr $end
$var wire 5 d in0 [4:0] $end
$var wire 5 e in1 [4:0] $end
$var wire 5 f out [4:0] $end
$var parameter 32 g width $end
$upscope $end
$scope module mux_2 $end
$var wire 1 : addr $end
$var wire 32 h in0 [31:0] $end
$var wire 32 i out [31:0] $end
$var wire 32 j in1 [31:0] $end
$var parameter 32 k width $end
$upscope $end
$scope module mux_3 $end
$var wire 1 / addr $end
$var wire 32 l in0 [31:0] $end
$var wire 32 m in1 [31:0] $end
$var wire 32 n out [31:0] $end
$var parameter 32 o width $end
$upscope $end
$scope module mux_4 $end
$var wire 1 p addr $end
$var wire 32 q in0 [31:0] $end
$var wire 32 r in1 [31:0] $end
$var wire 32 s out [31:0] $end
$var parameter 32 t width $end
$upscope $end
$scope module mux_5 $end
$var wire 1 2 addr $end
$var wire 32 u in0 [31:0] $end
$var wire 32 v in1 [31:0] $end
$var wire 32 w out [31:0] $end
$var parameter 32 x width $end
$upscope $end
$scope module pc $end
$var wire 1 " clk $end
$var wire 32 y data [31:0] $end
$var reg 32 z Q [31:0] $end
$upscope $end
$scope module sigext $end
$var wire 16 { in [15:0] $end
$var wire 32 | out [31:0] $end
$upscope $end
$upscope $end
$upscope $end
$enddefinitions $end
$comment Show the parameter values. $end
$dumpall
b11111 x
b11111 t
b11111 o
b11111 k
b100 g
b110 _
b1 ^
b11 ]
b0 \
b0 [
b101 Z
b100 Y
b101011 N
b100011 M
b10 L
b100 K
b1001 J
b0 I
b1010 !
$end
#0
$dumpvars
bx |
bx {
bx z
bx y
bx w
bx00 v
bx u
bx s
bx r
bx q
xp
bx n
bx m
bx l
bx j
bx i
bx h
bx f
bx e
bx d
bx c
bx b
bx a
bx `
bx X
bx W
bx V
bx U
bx T
bx S
bx R
bx Q
bx P
bx O
bx H
bx G
bx F
bx E
bx D
bx C
bx B
bx00 A
bx @
bx ?
bx >
b100 =
bx <
bx ;
x:
bx 9
bx 8
bx 7
bx 6
x5
bx 4
bx 3
x2
x1
x0
x/
x.
bx -
bx ,
bx +
bx *
x)
x(
bx '
x&
bx %
bx $
bx #
1"
$end
#2
b0 #
b0 ?
b0 G
b0 z
#3
b0xxxxxxxxxxxxxxxxxxxxxxxxxx00 v
b100 7
b100 >
b100 @
b100 q
#12
b1000000000000000000100 v
b0 e
b1000 d
b1 {
b1000 Q
b0 P
b1 b
b1001 H
b100100000010000000000000000001 3
b100100000010000000000000000001 F
#13
0p
b100 <
b100 X
b100 c
0)
1(
1:
01
00
0/
05
02
b0 ;
b0 O
b0 a
b100 A
b0x000 -
b0x000 U
b0x000 f
b1 '
b1 j
b1 |
b0 +
b0 R
b0 V
#14
b100 %
b100 s
b100 u
b1000 -
b1000 U
b1000 f
b1 9
b1 W
b1 i
b1000 6
b1000 B
b1000 r
#15
0&
0.
b1 8
b1 E
b1 `
b1 l
b100 $
b100 w
b100 y
#16
b1 ,
b1 T
b1 n
#23
bz 4
bz D
bz m
#50
0"
#100
1"
#101
b100 #
b100 ?
b100 G
b100 z
#102
b1 *
b1 C
b1 S
b1 h
b1000 7
b1000 >
b1000 @
b1000 q
#103
b1000 %
b1000 s
b1000 u
b1100 6
b1100 B
b1100 r
#104
b1000 $
b1000 w
b1000 y
#111
b1001000000000000001100 v
b1001 d
b11 {
b1001 Q
b11 b
b100100000010010000000000000011 3
b100100000010010000000000000011 F
#112
b1100 A
b1001 -
b1001 U
b1001 f
b11 '
b11 j
b11 |
bx *
bx C
bx S
bx h
#113
b11 9
b11 W
b11 i
b10100 6
b10100 B
b10100 r
#114
b11 8
b11 E
b11 `
b11 l
#115
b11 ,
b11 T
b11 n
#150
0"
#200
1"
#201
b1000 #
b1000 ?
b1000 G
b1000 z
#202
b1100 7
b1100 >
b1100 @
b1100 q
b11 *
b11 C
b11 S
b11 h
#203
b1100 %
b1100 s
b1100 u
b11000 6
b11000 B
b11000 r
#204
b1100 $
b1100 w
b1100 y
#211
b1011000000000000010000 v
b1011 d
b100 {
b1011 Q
b100 b
b100100000010110000000000000100 3
b100100000010110000000000000100 F
#212
b10000 A
b1011 -
b1011 U
b1011 f
b100 '
b100 j
b100 |
bx *
bx C
bx S
bx h
#213
b100 9
b100 W
b100 i
b11100 6
b11100 B
b11100 r
#214
b100 8
b100 E
b100 `
b100 l
#215
b100 ,
b100 T
b100 n
#250
0"
#300
1"
#301
b1100 #
b1100 ?
b1100 G
b1100 z
#302
b100 *
b100 C
b100 S
b100 h
b10000 7
b10000 >
b10000 @
b10000 q
#303
b10000 %
b10000 s
b10000 u
b100000 6
b100000 B
b100000 r
#304
b10000 $
b10000 w
b10000 y
#311
b100001001010100000010000000 v
b1010 e
b1001 d
b101000000100000 {
b1001 Q
b1000 P
b100000 b
b0 H
b1000010010101000000100000 3
b1000010010101000000100000 F
#312
1)
0:
b10 ;
b10 O
b10 a
b10100000010000000 A
b1001 -
b1001 U
b1001 f
b101000000100000 '
b101000000100000 j
b101000000100000 |
b11 *
b11 C
b11 S
b11 h
b1 +
b1 R
b1 V
#313
b101 8
b101 E
b101 `
b101 l
b1010 -
b1010 U
b1010 f
b11 9
b11 W
b11 i
b10100000010010000 6
b10100000010010000 B
b10100000010010000 r
#314
b100 8
b100 E
b100 `
b100 l
b101 ,
b101 T
b101 n
#315
b100 ,
b100 T
b100 n
#350
0"
#400
1"
#401
b10000 #
b10000 ?
b10000 G
b10000 z
#402
b10100 7
b10100 >
b10100 @
b10100 q
#403
b10100 %
b10100 s
b10100 u
b10100000010010100 6
b10100000010010100 B
b10100000010010100 r
#404
b10100 $
b10100 w
b10100 y
#411
b101001011000000000000000100 v
b0 e
b1011 d
b1 {
b1011 Q
b1010 P
b1 b
b100 H
b10001010010110000000000000001 3
b10001010010110000000000000001 F
#412
x)
0(
x/
15
b1 ;
b1 O
b1 a
b100 A
b0 -
b0 U
b0 f
b1 '
b1 j
b1 |
b100 *
b100 C
b100 S
b100 h
b100 +
b100 R
b100 V
#413
b110 <
b110 X
b110 c
b111 8
b111 E
b111 `
b111 l
b0x0xx -
b0x0xx U
b0x0xx f
bx ,
bx T
bx n
b11000 6
b11000 B
b11000 r
b100 9
b100 W
b100 i
#414
1p
1&
b0 8
b0 E
b0 `
b0 l
#415
b11000 %
b11000 s
b11000 u
#416
b11000 $
b11000 w
b11000 y
#450
0"
#500
1"
#501
b11000 #
b11000 ?
b11000 G
b11000 z
#502
b11100 7
b11100 >
b11100 @
b11100 q
#503
b100000 6
b100000 B
b100000 r
#504
b100000 %
b100000 s
b100000 u
#505
b100000 $
b100000 w
b100000 y
#511
b100001001010000000010001000 v
b1000 e
b1001 d
b100000000100010 {
b1001 Q
b1000 P
b100010 b
b0 H
b1000010010100000000100010 3
b1000010010100000000100010 F
#512
0p
1)
1(
0/
05
b10 ;
b10 O
b10 a
b10000000010001000 A
b100x -
b100x U
b100x f
b100000000100010 '
b100000000100010 j
b100000000100010 |
b11 *
b11 C
b11 S
b11 h
b1 +
b1 R
b1 V
#513
0&
1.
b11111111111111111111111111111101 8
b11111111111111111111111111111101 E
b11111111111111111111111111111101 `
b11111111111111111111111111111101 l
b11100 %
b11100 s
b11100 u
b1000 -
b1000 U
b1000 f
b0 ,
b0 T
b0 n
b10000000010100100 6
b10000000010100100 B
b10000000010100100 r
b11 9
b11 W
b11 i
#514
b11111111111111111111111111111110 8
b11111111111111111111111111111110 E
b11111111111111111111111111111110 `
b11111111111111111111111111111110 l
b11111111111111111111111111111101 ,
b11111111111111111111111111111101 T
b11111111111111111111111111111101 n
b11100 $
b11100 w
b11100 y
#515
b11111111111111111111111111111110 ,
b11111111111111111111111111111110 T
b11111111111111111111111111111110 n
#550
0"
#600
1"
#601
b11100 #
b11100 ?
b11100 G
b11100 z
#602
b11111111111111111111111111111110 +
b11111111111111111111111111111110 R
b11111111111111111111111111111110 V
b100000 7
b100000 >
b100000 @
b100000 q
#603
0.
b11111111111111111111111111111011 8
b11111111111111111111111111111011 E
b11111111111111111111111111111011 `
b11111111111111111111111111111011 l
b100000 %
b100000 s
b100000 u
b10000000010101000 6
b10000000010101000 B
b10000000010101000 r
#604
b11111111111111111111111111111011 ,
b11111111111111111111111111111011 T
b11111111111111111111111111111011 n
b100000 $
b100000 w
b100000 y
#611
b0xxxxxxxxxxxxxxxxxxxxxxxxxx00 v
bx e
bx d
bx {
bx Q
bx P
bx b
bx H
bx 3
bx F
#612
bx00 A
bx -
bx U
bx f
bx '
bx j
bx |
bx *
bx C
bx S
bx h
bx +
bx R
bx V
#613
x.
bx 8
bx E
bx `
bx l
bx 6
bx B
bx r
bx 9
bx W
bx i
#614
bx ,
bx T
bx n
#650
0"
#700
1"
#701
b100000 #
b100000 ?
b100000 G
b100000 z
#702
b100100 7
b100100 >
b100100 @
b100100 q
#703
b100100 %
b100100 s
b100100 u
#704
b100100 $
b100100 w
b100100 y
#750
0"
#800
1"
#801
b100100 #
b100100 ?
b100100 G
b100100 z
#802
b101000 7
b101000 >
b101000 @
b101000 q
#803
b101000 %
b101000 s
b101000 u
#804
b101000 $
b101000 w
b101000 y
#850
0"
#900
1"
#901
b101000 #
b101000 ?
b101000 G
b101000 z
#902
b101100 7
b101100 >
b101100 @
b101100 q
#903
b101100 %
b101100 s
b101100 u
#904
b101100 $
b101100 w
b101100 y
#950
0"
#1000
1"
#1001
b101100 #
b101100 ?
b101100 G
b101100 z
#1002
b110000 7
b110000 >
b110000 @
b110000 q
#1003
b110000 %
b110000 s
b110000 u
#1004
b110000 $
b110000 w
b110000 y
#1050
0"
#1100
1"
#1101
b110000 #
b110000 ?
b110000 G
b110000 z
#1102
b110100 7
b110100 >
b110100 @
b110100 q
#1103
b110100 %
b110100 s
b110100 u
#1104
b110100 $
b110100 w
b110100 y
#1150
0"
#1200
1"
#1201
b110100 #
b110100 ?
b110100 G
b110100 z
#1202
b111000 7
b111000 >
b111000 @
b111000 q
#1203
b111000 %
b111000 s
b111000 u
#1204
b111000 $
b111000 w
b111000 y
#1250
0"
#1300
1"
#1301
b111000 #
b111000 ?
b111000 G
b111000 z
#1302
b111100 7
b111100 >
b111100 @
b111100 q
#1303
b111100 %
b111100 s
b111100 u
#1304
b111100 $
b111100 w
b111100 y
#1350
0"
#1400
1"
#1401
b111100 #
b111100 ?
b111100 G
b111100 z
#1402
b1000000 7
b1000000 >
b1000000 @
b1000000 q
#1403
b1000000 %
b1000000 s
b1000000 u
#1404
b1000000 $
b1000000 w
b1000000 y
#1450
0"
#1500
1"
#1501
b1000000 #
b1000000 ?
b1000000 G
b1000000 z
#1502
b1000100 7
b1000100 >
b1000100 @
b1000100 q
#1503
b1000100 %
b1000100 s
b1000100 u
#1504
b1000100 $
b1000100 w
b1000100 y
#1550
0"
#1600
1"
#1601
b1000100 #
b1000100 ?
b1000100 G
b1000100 z
#1602
b1001000 7
b1001000 >
b1001000 @
b1001000 q
#1603
b1001000 %
b1001000 s
b1001000 u
#1604
b1001000 $
b1001000 w
b1001000 y
#1650
0"
#1700
1"
#1701
b1001000 #
b1001000 ?
b1001000 G
b1001000 z
#1702
b1001100 7
b1001100 >
b1001100 @
b1001100 q
#1703
b1001100 %
b1001100 s
b1001100 u
#1704
b1001100 $
b1001100 w
b1001100 y
#1750
0"
#1800
1"
#1801
b1001100 #
b1001100 ?
b1001100 G
b1001100 z
#1802
b1010000 7
b1010000 >
b1010000 @
b1010000 q
#1803
b1010000 %
b1010000 s
b1010000 u
#1804
b1010000 $
b1010000 w
b1010000 y
#1850
0"
#1900
1"
#1901
b1010000 #
b1010000 ?
b1010000 G
b1010000 z
#1902
b1010100 7
b1010100 >
b1010100 @
b1010100 q
#1903
b1010100 %
b1010100 s
b1010100 u
#1904
b1010100 $
b1010100 w
b1010100 y
#1950
0"
#2000
1"
#2001
b1010100 #
b1010100 ?
b1010100 G
b1010100 z
#2002
b1011000 7
b1011000 >
b1011000 @
b1011000 q
#2003
b1011000 %
b1011000 s
b1011000 u
#2004
b1011000 $
b1011000 w
b1011000 y
#2050
0"
#2100
1"
#2101
b1011000 #
b1011000 ?
b1011000 G
b1011000 z
#2102
b1011100 7
b1011100 >
b1011100 @
b1011100 q
#2103
b1011100 %
b1011100 s
b1011100 u
#2104
b1011100 $
b1011100 w
b1011100 y
#2150
0"
#2200
1"
#2201
b1011100 #
b1011100 ?
b1011100 G
b1011100 z
#2202
b1100000 7
b1100000 >
b1100000 @
b1100000 q
#2203
b1100000 %
b1100000 s
b1100000 u
#2204
b1100000 $
b1100000 w
b1100000 y
#2250
0"
#2300
1"
#2301
b1100000 #
b1100000 ?
b1100000 G
b1100000 z
#2302
b1100100 7
b1100100 >
b1100100 @
b1100100 q
#2303
b1100100 %
b1100100 s
b1100100 u
#2304
b1100100 $
b1100100 w
b1100100 y
#2350
0"
#2400
1"
#2401
b1100100 #
b1100100 ?
b1100100 G
b1100100 z
#2402
b1101000 7
b1101000 >
b1101000 @
b1101000 q
#2403
b1101000 %
b1101000 s
b1101000 u
#2404
b1101000 $
b1101000 w
b1101000 y
#2450
0"
#2500
1"
#2501
b1101000 #
b1101000 ?
b1101000 G
b1101000 z
#2502
b1101100 7
b1101100 >
b1101100 @
b1101100 q
#2503
b1101100 %
b1101100 s
b1101100 u
#2504
b1101100 $
b1101100 w
b1101100 y
#2550
0"
#2600
1"
#2601
b1101100 #
b1101100 ?
b1101100 G
b1101100 z
#2602
b1110000 7
b1110000 >
b1110000 @
b1110000 q
#2603
b1110000 %
b1110000 s
b1110000 u
#2604
b1110000 $
b1110000 w
b1110000 y
#2650
0"
#2700
1"
#2701
b1110000 #
b1110000 ?
b1110000 G
b1110000 z
#2702
b1110100 7
b1110100 >
b1110100 @
b1110100 q
#2703
b1110100 %
b1110100 s
b1110100 u
#2704
b1110100 $
b1110100 w
b1110100 y
#2750
0"
#2800
1"
#2801
b1110100 #
b1110100 ?
b1110100 G
b1110100 z
#2802
b1111000 7
b1111000 >
b1111000 @
b1111000 q
#2803
b1111000 %
b1111000 s
b1111000 u
#2804
b1111000 $
b1111000 w
b1111000 y
#2850
0"
#2900
1"
#2901
b1111000 #
b1111000 ?
b1111000 G
b1111000 z
#2902
b1111100 7
b1111100 >
b1111100 @
b1111100 q
#2903
b1111100 %
b1111100 s
b1111100 u
#2904
b1111100 $
b1111100 w
b1111100 y
#2950
0"
#3000
1"
#3001
b1111100 #
b1111100 ?
b1111100 G
b1111100 z
#3002
b10000000 7
b10000000 >
b10000000 @
b10000000 q
#3003
b10000000 %
b10000000 s
b10000000 u
#3004
b10000000 $
b10000000 w
b10000000 y
#3050
0"
#3100
1"
#3101
b10000000 #
b10000000 ?
b10000000 G
b10000000 z
#3102
b10000100 7
b10000100 >
b10000100 @
b10000100 q
#3103
b10000100 %
b10000100 s
b10000100 u
#3104
b10000100 $
b10000100 w
b10000100 y
#3150
0"
#3200
1"
#3201
b10000100 #
b10000100 ?
b10000100 G
b10000100 z
#3202
b10001000 7
b10001000 >
b10001000 @
b10001000 q
#3203
b10001000 %
b10001000 s
b10001000 u
#3204
b10001000 $
b10001000 w
b10001000 y
#3250
0"
#3300
1"
#3301
b10001000 #
b10001000 ?
b10001000 G
b10001000 z
#3302
b10001100 7
b10001100 >
b10001100 @
b10001100 q
#3303
b10001100 %
b10001100 s
b10001100 u
#3304
b10001100 $
b10001100 w
b10001100 y
#3350
0"
#3400
1"
#3401
b10001100 #
b10001100 ?
b10001100 G
b10001100 z
#3402
b10010000 7
b10010000 >
b10010000 @
b10010000 q
#3403
b10010000 %
b10010000 s
b10010000 u
#3404
b10010000 $
b10010000 w
b10010000 y
#3450
0"
#3500
1"
#3501
b10010000 #
b10010000 ?
b10010000 G
b10010000 z
#3502
b10010100 7
b10010100 >
b10010100 @
b10010100 q
#3503
b10010100 %
b10010100 s
b10010100 u
#3504
b10010100 $
b10010100 w
b10010100 y
#3550
0"
#3600
1"
#3601
b10010100 #
b10010100 ?
b10010100 G
b10010100 z
#3602
b10011000 7
b10011000 >
b10011000 @
b10011000 q
#3603
b10011000 %
b10011000 s
b10011000 u
#3604
b10011000 $
b10011000 w
b10011000 y
#3650
0"
#3700
1"
#3701
b10011000 #
b10011000 ?
b10011000 G
b10011000 z
#3702
b10011100 7
b10011100 >
b10011100 @
b10011100 q
#3703
b10011100 %
b10011100 s
b10011100 u
