单周期多周期CPU设计/Single Cycle Processor/include/RAM.v
//有写使能和输出使能，可以同时读一个和写一个
//输出和写入有1个时间单位的延时
module RAM(R_data,W_data,Addr,MemWr,MemRd);
input [31:0] Addr,W_data;
input MemWr, MemRd;
output [31:0] R_data;

reg [7:0] mem [16'hffff:0]; //size:2^16 x Byte =64KB

//输出的状态
assign #1 R_data = MemRd? {mem[Addr+3],mem[Addr+2],mem[Addr+1],mem[Addr]} : 32'hzzzz; //连续赋值assign始终处于活动状态

//写入的状态
always @(posedge MemWr ) begin
    #1 
    mem[Addr+3] <= W_data[31:24];
    mem[Addr+2] <= W_data[23:16];
    mem[Addr+1] <= W_data[15:8];
    mem[Addr] <= W_data[7:0];
end

endmodule

单周期多周期CPU设计/Single Cycle Processor/testbench/RAM_tb.v
`timescale 10ns/10ns
`include "../include/RAM.v"
module RAM_tb;
    reg [31:0] Addr;
    reg [31:0] W_data;
    reg MemWr, MemRd;
    wire [31:0] R_data;
    parameter clk_period = 10;
    integer  i;   

    initial begin
        $dumpfile("../vcd/RAM_tb.vcd");              // 指定记录模拟波形的文件
        $dumpvars(0, RAM_tb);          // 指定记录的模块层级
        MemWr <= 0;
        MemRd <= 0;
        Addr <= 32'h0;
        W_data <= 32'h23A0;

        //写入数据
        fork   
            repeat(3) #10 Addr = Addr + 1;
            repeat(10) #7 W_data = W_data + 1;
            repeat(5) #(clk_period/2) MemWr = ~MemWr;
        join

        //把刚才写的数据显示一下
        for (i=0; i<=3; i=i+1) begin
            $display("%h",ram.mem[i]);
        end       


        #30
        Addr <= 32'h0;
        fork
            repeat(3) #10 Addr = Addr + 1;
            repeat(5) #(clk_period/2) MemRd= ~MemRd;
        join
        
        #6000 $finish;  // 6000个单位时间后结束模拟
    end


    //always #(clk_period/2) MemRd = ~MemRd;   

    RAM ram(.Addr(Addr),.W_data(W_data),.MemWr(MemWr),.MemRd(MemRd),.R_data(R_data));


endmodule

单周期多周期CPU设计/Single Cycle Processor/vcd/RAM_tb.vcd
$date
	Wed Jan 25 13:51:57 2023
$end
$version
	Icarus Verilog
$end
$timescale
	10ns
$end
$scope module RAM_tb $end
$var wire 32 ! R_data [31:0] $end
$var parameter 32 " clk_period $end
$var reg 32 # Addr [31:0] $end
$var reg 1 $ MemRd $end
$var reg 1 % MemWr $end
$var reg 32 & W_data [31:0] $end
$var integer 32 ' i [31:0] $end
$scope module ram $end
$var wire 32 ( Addr [31:0] $end
$var wire 1 $ MemRd $end
$var wire 1 % MemWr $end
$var wire 32 ) W_data [31:0] $end
$var wire 32 * R_data [31:0] $end
$upscope $end
$upscope $end
$enddefinitions $end
$comment Show the parameter values. $end
$dumpall
b1010 "
$end
#0
$dumpvars
bz *
b10001110100000 )
b0 (
bx '
b10001110100000 &
0%
0$
b0 #
bz !
$end
#5
1%
#7
b10001110100001 &
b10001110100001 )
#10
0%
b1 #
b1 (
#14
b10001110100010 &
b10001110100010 )
#15
1%
#20
0%
b10 #
b10 (
#21
b10001110100011 &
b10001110100011 )
#25
1%
#28
b10001110100100 &
b10001110100100 )
#30
b11 #
b11 (
#35
b10001110100101 &
b10001110100101 )
#42
b10001110100110 &
b10001110100110 )
#49
b10001110100111 &
b10001110100111 )
#56
b10001110101000 &
b10001110101000 )
#63
b10001110101001 &
b10001110101001 )
#70
b100 '
b10001110101010 &
b10001110101010 )
#100
b0 #
b0 (
#105
b10001110100000 !
b10001110100000 *
1$
#110
bz !
bz *
0$
b1 #
b1 (
#115
b10001110100010 !
b10001110100010 *
1$
#120
bz !
bz *
0$
b10 #
b10 (
#125
b10001110100011 !
b10001110100011 *
1$
#130
bx !
bx *
b11 #
b11 (
