单周期多周期CPU设计/Multi Cycle Processor/include/SigExt.v
//带符号位扩展有0.1时间单位的延时
module SigExt(in,out);
input wire signed [15:0] in;
output wire signed [31:0] out;

assign #0.1 out = {{16{in[15]}}, in};


endmodule

单周期多周期CPU设计/Multi Cycle Processor/include/mux4.v
//多路选择器产生选通规定有0.1个时间单位的延时
module mux4(in0,in1,in2,in3,out,addr);
parameter width = 31;
input [width:0] in0, in1, in2, in3;
input [1:0] addr;
output reg [width:0] out;

always @(addr or in0 or in1 or in2 or in3) begin
    #0.1
    case(addr)
    2'b00: out <= in0;
    2'b01: out <= in1;
    2'b10: out <= in2;
    2'b11: out <= in3;
    endcase
end
endmodule

单周期多周期CPU设计/Multi Cycle Processor/include/mux2.v
//parameter指定输入的位数
//多路选择器产生选通规定有0.1个时间单位的延时
module mux2(in0,in1,out,addr);
parameter width = 31;
input [width:0] in0, in1;
input addr;
output [width:0] out;

assign #0.1 out = addr? in1 : in0;

endmodule

单周期多周期CPU设计/Multi Cycle Processor/include/Reg.v
//用来生成所有的寄存器
//写数据设置有0.1个时间单位的延迟
//读数据输出类型为reg，一直可读
module Reg(clk,data,Wr,Q);
    input clk, Wr;
    input [31:0] data;
    output reg [31:0] Q;

    always @(posedge clk ) begin
        #0.1
        if(Wr)
            Q <=  data;
    end
endmodule

单周期多周期CPU设计/Multi Cycle Processor/include/RF.v
//只有写使能，没有输出使能
//可以同时读两个寄存器，写一个寄存器
//寄存器堆RF有32个32位寄存器
//任何时候都可以读，时钟上跳沿来写数据
//写数据和读数据都设置有0.1个时间单位的延迟
module RF(R_Reg1,R_Reg2,W_Reg,W_data,R_data1,R_data2,clk,RegWr);
input [4:0] R_Reg1, R_Reg2, W_Reg;
input [31:0] W_data;
input clk, RegWr;
output [31:0] R_data1, R_data2;

reg [31:0] RF [31:0];//注意第二个是元素个数不是位宽

assign #0.1 R_data1 = RF[R_Reg1];
assign #0.1 R_data2 = RF[R_Reg2];

always @(posedge clk ) begin
    if(RegWr)
        #0.1 RF[W_Reg] <= W_data;
end

endmodule

单周期多周期CPU设计/Multi Cycle Processor/include/Mem.v
//有写使能和输出使能，可以同时读一个和写一个
//输出和写入有1个时间单位的延时
module Mem(R_data,W_data,Addr,MemWr,MemRd);
input [31:0] Addr,W_data;
input MemWr, MemRd;
output [31:0] R_data;

reg [7:0] data [16'hffff:0]; //size:2^16 x Byte =64KB

//输出的状态
assign #1 R_data = MemRd? {data[Addr+3],data[Addr+2],data[Addr+1],data[Addr]} : 32'hzzzz; //连续赋值assign始终处于活动状态

//写入的状态
always @(posedge MemWr ) begin
    #1 
    data[Addr+3] <= W_data[31:24];
    data[Addr+2] <= W_data[23:16];
    data[Addr+1] <= W_data[15:8];
    data[Addr] <= W_data[7:0];
end

endmodule

单周期多周期CPU设计/Multi Cycle Processor/include/ALU.v
//ALU计算有0.1时间单位的延时
module ALU(ALU_a,ALU_b,ALUCtrl,Zero,O,ALU_c);
input [31:0] ALU_a,ALU_b;
input [2:0] ALUCtrl;
output reg [31:0] ALU_c;
output reg Zero;
output reg O;

parameter ALU_pause=0,
          AND=3'b000,//
          OR=3'b001,//
          ADD=3'b100,//
          SUB=3'b110,//
          NOR=3'b011,//
          ADDU=3'b101;

always @(ALU_a or ALU_b or ALUCtrl) begin
    #0.1
    case(ALUCtrl)
        AND: ALU_c <= ALU_a & ALU_b;
        OR: ALU_c <= ALU_a | ALU_b;
        ADD: {O,ALU_c} <= ALU_a + ALU_b;
        SUB: {O,ALU_c} <= ALU_a - ALU_b;
        NOR: ALU_c <= ~ (ALU_a | ALU_b);
        ADDU: ALU_c <= ALU_a + ALU_b;
    endcase
end

always @(ALU_c) begin
    if (ALU_c == 0)
        Zero <= 1;
    else 
        Zero <= 0;
end

endmodule

单周期多周期CPU设计/Multi Cycle Processor/include/ALU_Ctrl.v
//产生ALUCtrl信号需要0.1时间单位的延时
module ALU_Ctrl (ALUOp,func,ALUCtrl);
input [5:0] func;
input [1:0] ALUOp;
output reg [2:0] ALUCtrl;

always @(func or ALUOp) begin
    #0.1
    casex(ALUOp) 
        2'b00: ALUCtrl <= 100;
        2'b01: ALUCtrl <= 110;
        2'b1x: begin
          case (func)
            6'b100000: ALUCtrl <= 100;
            6'b100001: ALUCtrl <= 101;
            6'b100010: ALUCtrl <= 110;
            6'b100100: ALUCtrl <= 000;
            6'b100101: ALUCtrl <= 001;
            6'b101010: ALUCtrl <= 011;
          endcase
        end
    endcase
end
endmodule

单周期多周期CPU设计/Multi Cycle Processor/include/CU_micro.v
//`include "mux4.v"
//有0.1个时间单位的延时
module CU_micro(PCWr,PCWrCond,IorD,MemRd,MemWr,IRWr,MemtoReg,PCSrc,ALUOp,ALUSrcB,ALUSrcA,RegWr,RegDst,Op,clk);
    input [5:0] Op;
    input clk;
    output PCWr,PCWrCond,IorD,MemRd,MemWr,IRWr,MemtoReg,ALUSrcA,RegWr,RegDst;
    output [1:0] PCSrc;
    output [1:0] ALUOp;
    output [1:0] ALUSrcB;

    //内部的连线和部件
    wire [3:0] mux_out;//多路选择器输出
    wire [1:0] mux_addr;//选择mux的地址
    wire [2:0] decode;//译码器的输入
    wire [3:0] addr1; //转移使用组合逻辑输出线
    wire [3:0] addr2;
    wire j,beq,R_type,lw,sw,addiu;//组合逻辑的中间变量，判断输入的Opcode是什么
    //00为转移到0号单元，01为组合逻辑1转移，10为组合逻辑2转移，11为顺序执行
    reg [3:0] CMAR;//用来存储当前地址的位置，clk来的时候更新
    reg [14:0] rom [10:0]; //用来存放微指令
   
   
    initial begin
        $readmemb("../file/rom.txt",rom,0,10);
    end

    //rom输出
    assign #0.1 {PCWr,PCWrCond,IorD,MemRd,decode,ALUOp,ALUSrcB,ALUSrcA,RegWr,mux_addr} = rom[CMAR];
    //译码器
    assign #0.1 RegDst = (decode==3'b001)? 1 : 0;
    assign #0.1 PCSrc[0] = (decode==3'b010)? 1 : 0;
    assign #0.1 PCSrc[1] = (decode==3'b011)? 1 : 0;
    assign #0.1 MemtoReg = (decode==3'b100)? 1 : 0;
    assign #0.1 MemWr = (decode==3'b101)? 1 : 0;
    assign #0.1 IRWr = (decode==3'b110)? 1 : 0;

    //先计算组合逻辑中间变量
    assign #0.1 R_type = ~Op[5] && ~Op[4] && ~Op[3] && ~Op[2] && ~Op[1] && ~Op[0];
    assign #0.1 j =      ~Op[5] && ~Op[4] && ~Op[3] && ~Op[2] &&  Op[1] && ~Op[0];
    assign #0.1 beq =    ~Op[5] && ~Op[4] && ~Op[3] &&  Op[2] && ~Op[1] && ~Op[0];
    assign #0.1 lw =      Op[5] && ~Op[4] && ~Op[3] && ~Op[2] &&  Op[1] &&  Op[0];
    assign #0.1 sw =      Op[5] && ~Op[4] &&  Op[3] && ~Op[2] &&  Op[1] &&  Op[0];
    assign #0.1 addiu  = ~Op[5] && ~Op[4] &&  Op[3] && ~Op[2] && ~Op[1] &&  Op[0];
    //addr1组合逻辑
    assign #0.1 addr1[3] = j || beq;
    assign #0.1 addr1[2] = R_type;
    assign #0.1 addr1[1] = R_type || lw || sw || addiu;
    assign #0.1 addr1[0] = j;
    //addr2组合逻辑
    assign #0.1 addr2[3] = addiu;
    assign #0.1 addr2[2] = sw;
    assign #0.1 addr2[1] = lw || addiu;
    assign #0.1 addr2[0] = lw || sw;

    //多路选择器输出mux_addr
    mux4 #(3) MUX(.in0(4'b0),.in1(addr1),.in2(addr2),.in3(CMAR+4'b1),.out(mux_out),.addr(mux_addr));    
    
    always @(posedge clk) begin //时钟信号到达更新地址
        CMAR <= mux_out;
    end

endmodule

单周期多周期CPU设计/Multi Cycle Processor/include/CPU_micro.v
// `include "ALU_Ctrl.v"
// `include "ALU.v"
// `include "CU_micro.v"
// `include "Mem.v"
// `include "mux2.v"
// `include "mux4.v"
// `include "Reg.v"
// `include "RF.v"
// `include "SigExt.v"

module CPU_micro(clk);
input clk;

//控制信号线
wire PCWr,PCWrCond,IorD,MemRd,MemWr,IRWr,MemtoReg,ALUSrcA,RegWr,RegDst;
wire [1:0] PCSrc;
wire [1:0] ALUOp;
wire [1:0] ALUSrcB;
wire [2:0] ALUCtrl;
wire Zero,O;

wire [31:0] Inst;//指令线，紫色的
wire [31:0] PC_out;//PC线，蓝色的
wire [31:0] PC_in;
wire [31:0] ALU_a;//ALU线和ALU_Out的输出线，绿色的
wire [31:0] ALU_b;
wire [31:0] ALU_c;
wire [31:0] ALU_Out_out;
wire [31:0] mem_addr;//存储器mem相关连线
wire [31:0] mem_rd;
wire [31:0] mem_wd;
wire [31:0] SigExt_out;//移位器输出线,黄色
wire [31:0] MDR_out;//MDR输出线，黄色
wire [31:0] A_out;//A的输出线，黄色
wire [31:0] RF_data1;//RF有关的线，墨绿色
wire [31:0] RF_data2;
wire [31:0] RF_W_data;
wire [4:0] RF_W_Reg;

//控制器
CU_micro CU(.PCWr(PCWr), .PCWrCond(PCWrCond), .IorD(IorD), .MemRd(MemRd), .MemWr(MemWr), .IRWr(IRWr), .MemtoReg(MemtoReg), .PCSrc(PCSrc), .ALUOp(ALUOp), .ALUSrcB(ALUSrcB), .ALUSrcA(ALUSrcA), .RegWr(RegWr), .RegDst(RegDst), .Op(Inst[31:26]), .clk(clk));
ALU_Ctrl alu_ctrl(.ALUOp(ALUOp), .func(Inst[5:0]), .ALUCtrl(ALUCtrl));

//运算器
ALU alu(.ALU_a(ALU_a), .ALU_b(ALU_b), .ALUCtrl(ALUCtrl), .Zero(Zero), .O(O), .ALU_c(ALU_c));

//存储器
Mem mem(.R_data(mem_rd), .W_data(mem_wd), .Addr(mem_addr), .MemWr(MemWr), .MemRd(MemRd));

//寄存器堆
RF RegFile(.R_Reg1(Inst[25:21]), .R_Reg2(Inst[20:16]), .W_Reg(RF_W_Reg), .W_data(RF_W_data), .R_data1(RF_data1), .R_data2(RF_data2), .clk(clk), .RegWr(RegWr));

//寄存器
Reg PC(.clk(clk), .data(PC_in), .Wr(PCWr||(PCWrCond&&Zero)), .Q(PC_out));
Reg IR(.clk(clk), .data(mem_rd), .Wr(IRWr), .Q(Inst));
Reg MDR(.clk(clk), .data(mem_rd), .Wr(1'b1), .Q(MDR_out));
Reg A(.clk(clk), .data(RF_data1), .Wr(1'b1), .Q(A_out));
Reg B(.clk(clk), .data(RF_data2), .Wr(1'b1), .Q(mem_wd));
Reg ALU_Out(.clk(clk), .data(ALU_c), .Wr(1'b1), .Q(ALU_Out_out));

//多路选择器
mux2 mux2_1(.in0(PC_out), .in1(ALU_Out_out), .out(mem_addr), .addr(IorD));
mux2 mux2_2(.in0(ALU_Out_out), .in1(MDR_out), .out(RF_W_data), .addr(MemtoReg));
mux2 #(4) mux2_3(.in0(Inst[20:16]), .in1(Inst[15:11]), .out(RF_W_Reg), .addr(RegDst));
mux2 mux2_4(.in0(PC_out), .in1(A_out), .out(ALU_a), .addr(ALUSrcA));
mux4 mux4_1(.in0(mem_wd), .in1(32'h00000004), .in2(SigExt_out), .in3(SigExt_out<<2), .out(ALU_b), .addr(ALUSrcB));
mux4 mux4_2(.in0(ALU_c), .in1(ALU_Out_out), .in2({PC_out[31:28],Inst[25:0],2'b00}), .in3(32'hzzzzzzzz), .out(PC_in), .addr(PCSrc));

//移位器
SigExt sigext (.in(Inst[15:0]), .out(SigExt_out));

endmodule

单周期多周期CPU设计/Multi Cycle Processor/testbench/CPU_micro_run1_tb.v
`timescale 10ns/1ns
`include "../include/ALU_Ctrl.v"
`include "../include/ALU.v"
`include "../include/CU_micro.v"
`include "../include/Mem.v"
`include "../include/mux2.v"
`include "../include/mux4.v"
`include "../include/Reg.v"
`include "../include/RF.v"
`include "../include/SigExt.v"
`include "../include/CPU_micro.v"

module CPU_micro_run1_tb;
    //.txt
    // main:
    // 	addiu $t0,$0,1
    // 	addiu $t1,$0,3
    // 	addiu $t3,$0,4
    // 	add $t2,$t0,$t1
    // 	beq $t2,$t3,next
    // 	sub $t0,$t1,$t0
    // next:	
    // 	sub $t0,$t0,$t1	
    //指令第一条存在32'h00000000的位置
    reg clk;
    parameter clk_period = 10;

    initial begin
        $dumpfile("../vcd/CPU_micro_run1_tb.vcd");             
        $dumpvars(0, CPU_micro_run1_tb); 
        $readmemh("../file/run1.txt",cpu.mem.data);//设置存储器初值
        $readmemh("../file/run1_RF.txt",cpu.RegFile.RF);//设置RF初值,$0寄存器的值恒为0
        
        clk <= 1 ;
        #0.2 cpu.PC.Q <= 32'h0; //pc赋值
        cpu.CU.CMAR <= 4'b0000;

        // #10
        // $display("%h",cpu.RegFile.RF[8]);
        // #10
        // $display("%h",cpu.RegFile.RF[9]);

        #6000 $finish; 
    end

    always #(clk_period/2) clk = ~clk;

    CPU_micro cpu(.clk(clk));

endmodule

单周期多周期CPU设计/Multi Cycle Processor/vcd/CPU_micro_run1_tb.vcd
$date
	Tue Feb 28 15:07:34 2023
$end
$version
	Icarus Verilog
$end
$timescale
	1ns
$end
$scope module CPU_micro_run1_tb $end
$var parameter 32 ! clk_period $end
$var reg 1 " clk $end
$scope module cpu $end
$var wire 1 " clk $end
$var wire 32 # mem_wd [31:0] $end
$var wire 32 $ mem_rd [31:0] $end
$var wire 32 % mem_addr [31:0] $end
$var wire 1 & Zero $end
$var wire 32 ' SigExt_out [31:0] $end
$var wire 1 ( RegWr $end
$var wire 1 ) RegDst $end
$var wire 32 * RF_data2 [31:0] $end
$var wire 32 + RF_data1 [31:0] $end
$var wire 32 , RF_W_data [31:0] $end
$var wire 5 - RF_W_Reg [4:0] $end
$var wire 32 . PC_out [31:0] $end
$var wire 32 / PC_in [31:0] $end
$var wire 1 0 PCWrCond $end
$var wire 1 1 PCWr $end
$var wire 2 2 PCSrc [1:0] $end
$var wire 1 3 O $end
$var wire 1 4 MemtoReg $end
$var wire 1 5 MemWr $end
$var wire 1 6 MemRd $end
$var wire 32 7 MDR_out [31:0] $end
$var wire 1 8 IorD $end
$var wire 32 9 Inst [31:0] $end
$var wire 1 : IRWr $end
$var wire 32 ; A_out [31:0] $end
$var wire 32 < ALU_c [31:0] $end
$var wire 32 = ALU_b [31:0] $end
$var wire 32 > ALU_a [31:0] $end
$var wire 32 ? ALU_Out_out [31:0] $end
$var wire 2 @ ALUSrcB [1:0] $end
$var wire 1 A ALUSrcA $end
$var wire 2 B ALUOp [1:0] $end
$var wire 3 C ALUCtrl [2:0] $end
$scope module A $end
$var wire 1 D Wr $end
$var wire 1 " clk $end
$var wire 32 E data [31:0] $end
$var reg 32 F Q [31:0] $end
$upscope $end
$scope module ALU_Out $end
$var wire 1 G Wr $end
$var wire 1 " clk $end
$var wire 32 H data [31:0] $end
$var reg 32 I Q [31:0] $end
$upscope $end
$scope module B $end
$var wire 1 J Wr $end
$var wire 1 " clk $end
$var wire 32 K data [31:0] $end
$var reg 32 L Q [31:0] $end
$upscope $end
$scope module CU $end
$var wire 6 M Op [5:0] $end
$var wire 1 N R_type $end
$var wire 1 O addiu $end
$var wire 1 P beq $end
$var wire 1 " clk $end
$var wire 1 Q j $end
$var wire 1 R lw $end
$var wire 1 S sw $end
$var wire 4 T mux_out [3:0] $end
$var wire 2 U mux_addr [1:0] $end
$var wire 3 V decode [2:0] $end
$var wire 4 W addr2 [3:0] $end
$var wire 4 X addr1 [3:0] $end
$var wire 1 ( RegWr $end
$var wire 1 ) RegDst $end
$var wire 1 0 PCWrCond $end
$var wire 1 1 PCWr $end
$var wire 2 Y PCSrc [1:0] $end
$var wire 1 4 MemtoReg $end
$var wire 1 5 MemWr $end
$var wire 1 6 MemRd $end
$var wire 1 8 IorD $end
$var wire 1 : IRWr $end
$var wire 2 Z ALUSrcB [1:0] $end
$var wire 1 A ALUSrcA $end
$var wire 2 [ ALUOp [1:0] $end
$var reg 4 \ CMAR [3:0] $end
$scope module MUX $end
$var wire 2 ] addr [1:0] $end
$var wire 4 ^ in0 [3:0] $end
$var wire 4 _ in1 [3:0] $end
$var wire 4 ` in2 [3:0] $end
$var wire 4 a in3 [3:0] $end
$var parameter 32 b width $end
$var reg 4 c out [3:0] $end
$upscope $end
$upscope $end
$scope module IR $end
$var wire 1 : Wr $end
$var wire 1 " clk $end
$var wire 32 d data [31:0] $end
$var reg 32 e Q [31:0] $end
$upscope $end
$scope module MDR $end
$var wire 1 f Wr $end
$var wire 1 " clk $end
$var wire 32 g data [31:0] $end
$var reg 32 h Q [31:0] $end
$upscope $end
$scope module PC $end
$var wire 1 i Wr $end
$var wire 1 " clk $end
$var wire 32 j data [31:0] $end
$var reg 32 k Q [31:0] $end
$upscope $end
$scope module RegFile $end
$var wire 5 l R_Reg1 [4:0] $end
$var wire 5 m R_Reg2 [4:0] $end
$var wire 32 n R_data1 [31:0] $end
$var wire 32 o R_data2 [31:0] $end
$var wire 1 ( RegWr $end
$var wire 1 " clk $end
$var wire 32 p W_data [31:0] $end
$var wire 5 q W_Reg [4:0] $end
$upscope $end
$scope module alu $end
$var wire 32 r ALU_b [31:0] $end
$var wire 32 s ALU_a [31:0] $end
$var wire 3 t ALUCtrl [2:0] $end
$var parameter 3 u ADD $end
$var parameter 3 v ADDU $end
$var parameter 32 w ALU_pause $end
$var parameter 3 x AND $end
$var parameter 3 y NOR $end
$var parameter 3 z OR $end
$var parameter 3 { SUB $end
$var reg 32 | ALU_c [31:0] $end
$var reg 1 3 O $end
$var reg 1 & Zero $end
$upscope $end
$scope module alu_ctrl $end
$var wire 2 } ALUOp [1:0] $end
$var wire 6 ~ func [5:0] $end
$var reg 3 !" ALUCtrl [2:0] $end
$upscope $end
$scope module mem $end
$var wire 1 6 MemRd $end
$var wire 1 5 MemWr $end
$var wire 32 "" W_data [31:0] $end
$var wire 32 #" R_data [31:0] $end
$var wire 32 $" Addr [31:0] $end
$upscope $end
$scope module mux2_1 $end
$var wire 1 8 addr $end
$var wire 32 %" in0 [31:0] $end
$var wire 32 &" in1 [31:0] $end
$var wire 32 '" out [31:0] $end
$var parameter 32 (" width $end
$upscope $end
$scope module mux2_2 $end
$var wire 1 4 addr $end
$var wire 32 )" in0 [31:0] $end
$var wire 32 *" in1 [31:0] $end
$var wire 32 +" out [31:0] $end
$var parameter 32 ," width $end
$upscope $end
$scope module mux2_3 $end
$var wire 1 ) addr $end
$var wire 5 -" in0 [4:0] $end
$var wire 5 ." in1 [4:0] $end
$var wire 5 /" out [4:0] $end
$var parameter 32 0" width $end
$upscope $end
$scope module mux2_4 $end
$var wire 1 A addr $end
$var wire 32 1" in0 [31:0] $end
$var wire 32 2" in1 [31:0] $end
$var wire 32 3" out [31:0] $end
$var parameter 32 4" width $end
$upscope $end
$scope module mux4_1 $end
$var wire 2 5" addr [1:0] $end
$var wire 32 6" in0 [31:0] $end
$var wire 32 7" in1 [31:0] $end
$var wire 32 8" in3 [31:0] $end
$var wire 32 9" in2 [31:0] $end
$var parameter 32 :" width $end
$var reg 32 ;" out [31:0] $end
$upscope $end
$scope module mux4_2 $end
$var wire 2 <" addr [1:0] $end
$var wire 32 =" in0 [31:0] $end
$var wire 32 >" in1 [31:0] $end
$var wire 32 ?" in2 [31:0] $end
$var wire 32 @" in3 [31:0] $end
$var parameter 32 A" width $end
$var reg 32 B" out [31:0] $end
$upscope $end
$scope module sigext $end
$var wire 16 C" in [15:0] $end
$var wire 32 D" out [31:0] $end
$upscope $end
$upscope $end
$upscope $end
$enddefinitions $end
$comment Show the parameter values. $end
$dumpall
b11111 A"
b11111 :"
b11111 4"
b100 0"
b11111 ,"
b11111 ("
b110 {
b1 z
b11 y
b0 x
b0 w
b101 v
b100 u
b11 b
b1010 !
$end
#0
$dumpvars
bx D"
bx C"
bx B"
bz @"
bx00 ?"
bx >"
bx ="
bx <"
bx ;"
bx 9"
bx00 8"
b100 7"
bx 6"
bx 5"
bx 3"
bx 2"
bx 1"
bx /"
bx ."
bx -"
bx +"
bx *"
bx )"
bx '"
bx &"
bx %"
bx $"
bx #"
bx ""
bx !"
bx ~
bx }
bx |
bx t
bx s
bx r
bx q
bx p
bx o
bx n
bx m
bx l
bx k
bx j
xi
bx h
bx g
1f
bx e
bx d
bx c
bx a
bx `
bx _
b0 ^
bx ]
bx \
bx [
bx Z
bx Y
bx X
bx W
bx V
bx U
bx T
xS
xR
xQ
xP
xO
xN
bx M
bx L
bx K
1J
bx I
bx H
1G
bx F
bx E
1D
bx C
bx B
xA
bx @
bx ?
bx >
bx =
bx <
bx ;
x:
bx 9
x8
bx 7
x6
x5
x4
x3
bx 2
x1
x0
bx /
bx .
bx -
bx ,
bx +
bx *
x)
x(
bx '
x&
bx %
bx $
bx #
1"
$end
#2
b0xxxxxxxxxxxxxxxxxxxxxxxxxx00 ?"
b1 a
b0 \
b0 .
b0 k
b0 %"
b0 1"
#3
1i
11
00
08
16
b110 V
b0 B
b0 [
b0 }
b1 @
b1 Z
b1 5"
0A
0(
b11 U
b11 ]
#4
b100 C
b100 t
b100 !"
b100 =
b100 r
b100 ;"
b1 T
b1 c
0)
b0 2
b0 Y
b0 <"
04
05
1:
b0 %
b0 $"
b0 '"
b0 >
b0 s
b0 3"
#5
0&
03
b100 <
b100 H
b100 |
b100 ="
#6
b100 /
b100 j
b100 B"
#14
b100100000010000000000000000001 $
b100100000010000000000000000001 d
b100100000010000000000000000001 g
b100100000010000000000000000001 #"
#50
0"
#100
b10 a
b1 \
1"
#101
b1 C"
b1000000000000000000100 ?"
b0 ."
b1000 -"
b1000 m
b0 l
b1 ~
b1001 M
b10 T
b10 c
b100 ?
b100 I
b100 &"
b100 )"
b100 >"
b100100000010000000000000000001 7
b100100000010000000000000000001 h
b100100000010000000000000000001 *"
b100100000010000000000000000001 9
b100100000010000000000000000001 e
b100 .
b100 k
b100 %"
b100 1"
0i
01
06
b0 V
b11 @
b11 Z
b11 5"
b1 U
b1 ]
#102
bx00 =
bx00 r
bx00 ;"
bx T
bx c
b100 8"
1O
0N
0Q
0P
0R
0S
b1000 -
b1000 q
b1000 /"
b100 ,
b100 p
b100 +"
b1 '
b1 9"
b1 D"
b0 +
b0 E
b0 n
b100 %
b100 $"
b100 '"
b100 >
b100 s
b100 3"
0:
#103
b100 =
b100 r
b100 ;"
x3
bx <
bx H
bx |
bx ="
b10 X
b10 _
b1010 W
b1010 `
#104
03
b1000 <
b1000 H
b1000 |
b1000 ="
bx /
bx j
bx B"
b10 T
b10 c
#105
b1000 /
b1000 j
b1000 B"
#111
bz $
bz d
bz g
bz #"
#150
0"
#200
b11 a
b10 \
1"
#201
bz 7
bz h
bz *"
b0 ;
b0 F
b0 2"
b1000 ?
b1000 I
b1000 &"
b1000 )"
b1000 >"
b10 @
b10 Z
b10 5"
1A
b10 U
b10 ]
#202
b1 =
b1 r
b1 ;"
b1010 T
b1010 c
b1000 ,
b1000 p
b1000 +"
b0 >
b0 s
b0 3"
#203
b1 <
b1 H
b1 |
b1 ="
#204
b1 /
b1 j
b1 B"
#250
0"
#300
b1011 a
b1010 \
1"
#301
b1 ?
b1 I
b1 &"
b1 )"
b1 >"
b0 @
b0 Z
b0 5"
0A
1(
b0 U
b0 ]
#302
bx =
bx r
bx ;"
b0 T
b0 c
b1 ,
b1 p
b1 +"
b100 >
b100 s
b100 3"
#303
x3
bx <
bx H
bx |
bx ="
#304
bx /
bx j
bx B"
#350
0"
#400
b1 a
b0 \
1"
#401
bx ?
bx I
bx &"
bx )"
bx >"
1i
11
16
b110 V
b1 @
b1 Z
b1 5"
0(
b11 U
b11 ]
#402
b100 =
b100 r
b100 ;"
b1 T
b1 c
bx ,
bx p
bx +"
b1 *
b1 K
b1 o
1:
#403
03
b1000 <
b1000 H
b1000 |
b1000 ="
#404
b1000 /
b1000 j
b1000 B"
#411
b100100000010010000000000000011 $
b100100000010010000000000000011 d
b100100000010010000000000000011 g
b100100000010010000000000000011 #"
#450
0"
#500
b10 a
b1 \
1"
#501
b11 C"
b1001000000000000001100 ?"
b1001 -"
b1001 m
b11 ~
b10 T
b10 c
b1000 ?
b1000 I
b1000 &"
b1000 )"
b1000 >"
b1 #
b1 L
b1 ""
b1 6"
b100100000010010000000000000011 7
b100100000010010000000000000011 h
b100100000010010000000000000011 *"
b100100000010010000000000000011 9
b100100000010010000000000000011 e
b1000 .
b1000 k
b1000 %"
b1000 1"
0i
01
06
b0 V
b11 @
b11 Z
b11 5"
b1 U
b1 ]
#502
b1100 8"
b1001 -
b1001 q
b1001 /"
b1000 ,
b1000 p
b1000 +"
b11 '
b11 9"
b11 D"
bx *
bx K
bx o
b1000 %
b1000 $"
b1000 '"
b1000 >
b1000 s
b1000 3"
0:
#503
b1100 =
b1100 r
b1100 ;"
b1100 <
b1100 H
b1100 |
b1100 ="
#504
b10100 <
b10100 H
b10100 |
b10100 ="
b1100 /
b1100 j
b1100 B"
#505
b10100 /
b10100 j
b10100 B"
#511
bz $
bz d
bz g
bz #"
#550
0"
#600
b11 a
b10 \
1"
#601
bz 7
bz h
bz *"
bx #
bx L
bx ""
bx 6"
b10100 ?
b10100 I
b10100 &"
b10100 )"
b10100 >"
b10 @
b10 Z
b10 5"
1A
b10 U
b10 ]
#602
b11 =
b11 r
b11 ;"
b1010 T
b1010 c
b10100 ,
b10100 p
b10100 +"
b0 >
b0 s
b0 3"
#603
b11 <
b11 H
b11 |
b11 ="
#604
b11 /
b11 j
b11 B"
#650
0"
#700
b1011 a
b1010 \
1"
#701
b11 ?
b11 I
b11 &"
b11 )"
b11 >"
b0 @
b0 Z
b0 5"
0A
1(
b0 U
b0 ]
#702
bx =
bx r
bx ;"
b0 T
b0 c
b11 ,
b11 p
b11 +"
b1000 >
b1000 s
b1000 3"
#703
x3
bx <
bx H
bx |
bx ="
#704
bx /
bx j
bx B"
#750
0"
#800
b1 a
b0 \
1"
#801
bx ?
bx I
bx &"
bx )"
bx >"
1i
11
16
b110 V
b1 @
b1 Z
b1 5"
0(
b11 U
b11 ]
#802
b100 =
b100 r
b100 ;"
b1 T
b1 c
bx ,
bx p
bx +"
b11 *
b11 K
b11 o
1:
#803
03
b1100 <
b1100 H
b1100 |
b1100 ="
#804
b1100 /
b1100 j
b1100 B"
#811
b100100000010110000000000000100 $
b100100000010110000000000000100 d
b100100000010110000000000000100 g
b100100000010110000000000000100 #"
#850
0"
#900
b10 a
b1 \
1"
#901
b100 C"
b1011000000000000010000 ?"
b1011 -"
b1011 m
b100 ~
b10 T
b10 c
b1100 ?
b1100 I
b1100 &"
b1100 )"
b1100 >"
b11 #
b11 L
b11 ""
b11 6"
b100100000010110000000000000100 7
b100100000010110000000000000100 h
b100100000010110000000000000100 *"
b100100000010110000000000000100 9
b100100000010110000000000000100 e
b1100 .
b1100 k
b1100 %"
b1100 1"
0i
01
06
b0 V
b11 @
b11 Z
b11 5"
b1 U
b1 ]
#902
b1100 =
b1100 r
b1100 ;"
b10000 8"
b1011 -
b1011 q
b1011 /"
b1100 ,
b1100 p
b1100 +"
b100 '
b100 9"
b100 D"
bx *
bx K
bx o
b1100 %
b1100 $"
b1100 '"
b1100 >
b1100 s
b1100 3"
0:
#903
b10000 =
b10000 r
b10000 ;"
b11000 <
b11000 H
b11000 |
b11000 ="
#904
b11100 <
b11100 H
b11100 |
b11100 ="
b11000 /
b11000 j
b11000 B"
#905
b11100 /
b11100 j
b11100 B"
#911
bz $
bz d
bz g
bz #"
#950
0"
#1000
b11 a
b10 \
1"
#1001
bz 7
bz h
bz *"
bx #
bx L
bx ""
bx 6"
b11100 ?
b11100 I
b11100 &"
b11100 )"
b11100 >"
b10 @
b10 Z
b10 5"
1A
b10 U
b10 ]
#1002
b100 =
b100 r
b100 ;"
b1010 T
b1010 c
b11100 ,
b11100 p
b11100 +"
b0 >
b0 s
b0 3"
#1003
b100 <
b100 H
b100 |
b100 ="
#1004
b100 /
b100 j
b100 B"
#1050
0"
#1100
b1011 a
b1010 \
1"
#1101
b100 ?
b100 I
b100 &"
b100 )"
b100 >"
b0 @
b0 Z
b0 5"
0A
1(
b0 U
b0 ]
#1102
bx =
bx r
bx ;"
b0 T
b0 c
b100 ,
b100 p
b100 +"
b1100 >
b1100 s
b1100 3"
#1103
x3
bx <
bx H
bx |
bx ="
#1104
bx /
bx j
bx B"
#1150
0"
#1200
b1 a
b0 \
1"
#1201
bx ?
bx I
bx &"
bx )"
bx >"
1i
11
16
b110 V
b1 @
b1 Z
b1 5"
0(
b11 U
b11 ]
#1202
b100 =
b100 r
b100 ;"
b1 T
b1 c
bx ,
bx p
bx +"
b100 *
b100 K
b100 o
1:
#1203
03
b10000 <
b10000 H
b10000 |
b10000 ="
#1204
b10000 /
b10000 j
b10000 B"
#1211
b1000010010101000000100000 $
b1000010010101000000100000 d
b1000010010101000000100000 g
b1000010010101000000100000 #"
#1250
0"
#1300
b10 a
b1 \
1"
#1301
b101000000100000 C"
b100001001010100000010000000 ?"
b1010 ."
b1001 -"
b1001 m
b1000 l
b100000 ~
b0 M
b10 T
b10 c
b10000 ?
b10000 I
b10000 &"
b10000 )"
b10000 >"
b100 #
b100 L
b100 ""
b100 6"
b1000010010101000000100000 7
b1000010010101000000100000 h
b1000010010101000000100000 *"
b1000010010101000000100000 9
b1000010010101000000100000 e
b10000 .
b10000 k
b10000 %"
b10000 1"
0i
01
06
b0 V
b11 @
b11 Z
b11 5"
b1 U
b1 ]
#1302
b10000 =
b10000 r
b10000 ;"
b10100000010000000 8"
1N
0O
b1001 -
b1001 q
b1001 /"
b10000 ,
b10000 p
b10000 +"
b101000000100000 '
b101000000100000 9"
b101000000100000 D"
b11 *
b11 K
b11 o
b1 +
b1 E
b1 n
b10000 %
b10000 $"
b10000 '"
b10000 >
b10000 s
b10000 3"
0:
#1303
b10100000010000000 =
b10100000010000000 r
b10100000010000000 ;"
b100000 <
b100000 H
b100000 |
b100000 ="
b110 X
b110 _
b0 W
b0 `
