单周期多周期CPU设计/Multi Cycle Processor/include/SigExt.v
//带符号位扩展有0.1时间单位的延时
module SigExt(in,out);
input wire signed [15:0] in;
output wire signed [31:0] out;

assign #0.1 out = {{16{in[15]}}, in};


endmodule

单周期多周期CPU设计/Multi Cycle Processor/include/mux4.v
//多路选择器产生选通规定有0.1个时间单位的延时
module mux4(in0,in1,in2,in3,out,addr);
parameter width = 31;
input [width:0] in0, in1, in2, in3;
input [1:0] addr;
output reg [width:0] out;

always @(addr or in0 or in1 or in2 or in3) begin
    #0.1
    case(addr)
    2'b00: out <= in0;
    2'b01: out <= in1;
    2'b10: out <= in2;
    2'b11: out <= in3;
    endcase
end
endmodule

单周期多周期CPU设计/Multi Cycle Processor/include/mux2.v
//parameter指定输入的位数
//多路选择器产生选通规定有0.1个时间单位的延时
module mux2(in0,in1,out,addr);
parameter width = 31;
input [width:0] in0, in1;
input addr;
output [width:0] out;

assign #0.1 out = addr? in1 : in0;

endmodule

单周期多周期CPU设计/Multi Cycle Processor/include/Reg.v
//用来生成所有的寄存器
//写数据设置有0.1个时间单位的延迟
//读数据输出类型为reg，一直可读
module Reg(clk,data,Wr,Q);
    input clk, Wr;
    input [31:0] data;
    output reg [31:0] Q;

    always @(posedge clk ) begin
        #0.1
        if(Wr)
            Q <=  data;
    end
endmodule

单周期多周期CPU设计/Multi Cycle Processor/include/RF.v
//只有写使能，没有输出使能
//可以同时读两个寄存器，写一个寄存器
//寄存器堆RF有32个32位寄存器
//任何时候都可以读，时钟上跳沿来写数据
//写数据和读数据都设置有0.1个时间单位的延迟
module RF(R_Reg1,R_Reg2,W_Reg,W_data,R_data1,R_data2,clk,RegWr);
input [4:0] R_Reg1, R_Reg2, W_Reg;
input [31:0] W_data;
input clk, RegWr;
output [31:0] R_data1, R_data2;

reg [31:0] RF [31:0];//注意第二个是元素个数不是位宽

assign #0.1 R_data1 = RF[R_Reg1];
assign #0.1 R_data2 = RF[R_Reg2];

always @(posedge clk ) begin
    if(RegWr)
        #0.1 RF[W_Reg] <= W_data;
end

endmodule

单周期多周期CPU设计/Multi Cycle Processor/include/Mem.v
//有写使能和输出使能，可以同时读一个和写一个
//输出和写入有1个时间单位的延时
module Mem(R_data,W_data,Addr,MemWr,MemRd);
input [31:0] Addr,W_data;
input MemWr, MemRd;
output [31:0] R_data;

reg [7:0] data [16'hffff:0]; //size:2^16 x Byte =64KB

//输出的状态
assign #1 R_data = MemRd? {data[Addr+3],data[Addr+2],data[Addr+1],data[Addr]} : 32'hzzzz; //连续赋值assign始终处于活动状态

//写入的状态
always @(posedge MemWr ) begin
    #1 
    data[Addr+3] <= W_data[31:24];
    data[Addr+2] <= W_data[23:16];
    data[Addr+1] <= W_data[15:8];
    data[Addr] <= W_data[7:0];
end

endmodule

单周期多周期CPU设计/Multi Cycle Processor/include/ALU.v
//ALU计算有0.1时间单位的延时
module ALU(ALU_a,ALU_b,ALUCtrl,Zero,O,ALU_c);
input [31:0] ALU_a,ALU_b;
input [2:0] ALUCtrl;
output reg [31:0] ALU_c;
output reg Zero;
output reg O;

parameter ALU_pause=0,
          AND=3'b000,//
          OR=3'b001,//
          ADD=3'b100,//
          SUB=3'b110,//
          NOR=3'b011,//
          ADDU=3'b101;

always @(ALU_a or ALU_b or ALUCtrl) begin
    #0.1
    case(ALUCtrl)
        AND: ALU_c <= ALU_a & ALU_b;
        OR: ALU_c <= ALU_a | ALU_b;
        ADD: {O,ALU_c} <= ALU_a + ALU_b;
        SUB: {O,ALU_c} <= ALU_a - ALU_b;
        NOR: ALU_c <= ~ (ALU_a | ALU_b);
        ADDU: ALU_c <= ALU_a + ALU_b;
    endcase
end

always @(ALU_c) begin
    if (ALU_c == 0)
        Zero <= 1;
    else 
        Zero <= 0;
end

endmodule

单周期多周期CPU设计/Multi Cycle Processor/include/ALU_Ctrl.v
//产生ALUCtrl信号需要0.1时间单位的延时
module ALU_Ctrl (ALUOp,func,ALUCtrl);
input [5:0] func;
input [1:0] ALUOp;
output reg [2:0] ALUCtrl;

always @(func or ALUOp) begin
    #0.1
    casex(ALUOp) 
        2'b00: ALUCtrl <= 100;
        2'b01: ALUCtrl <= 110;
        2'b1x: begin
          case (func)
            6'b100000: ALUCtrl <= 100;
            6'b100001: ALUCtrl <= 101;
            6'b100010: ALUCtrl <= 110;
            6'b100100: ALUCtrl <= 000;
            6'b100101: ALUCtrl <= 001;
            6'b101010: ALUCtrl <= 011;
          endcase
        end
    endcase
end
endmodule

单周期多周期CPU设计/Multi Cycle Processor/include/CU_logic.v
//组合逻辑的同步控制
//产生控制信号有0.1个时间单位的延时
module CU_logic(PCWr,PCWrCond,IorD,MemRd,MemWr,IRWr,MemtoReg,PCSrc,ALUOp,ALUSrcB,ALUSrcA,RegWr,RegDst,Op,clk);
    input [5:0] Op;
    input clk;

    output PCWr,PCWrCond,IorD,MemRd,MemWr,IRWr,MemtoReg,ALUSrcA,RegWr,RegDst;
    output [1:0] PCSrc;
    output [1:0] ALUOp;
    output [1:0] ALUSrcB;

    reg [3:0] S;//目前的状态
    wire [3:0] NS;//下一个状态
    wire [19:0] P;//中间与门的输出

    //组合逻辑上方的与门
    //P[0]-P[9]是代表0-9的状态
    assign #0.1 P[0] = ~S[3] && ~S[2] && ~S[1] && ~S[0]; //0000
    assign #0.1 P[1] = ~S[3] && ~S[2] && ~S[1] &&  S[0]; //0001
    assign #0.1 P[2] = ~S[3] && ~S[2] &&  S[1] && ~S[0]; //0010
    assign #0.1 P[3] = ~S[3] && ~S[2] &&  S[1] &&  S[0]; //0011
    assign #0.1 P[4] = ~S[3] &&  S[2] && ~S[1] && ~S[0]; //0100
    assign #0.1 P[5] = ~S[3] &&  S[2] && ~S[1] &&  S[0]; //0101
    assign #0.1 P[6] = ~S[3] &&  S[2] &&  S[1] && ~S[0]; //0110
    assign #0.1 P[7] = ~S[3] &&  S[2] &&  S[1] &&  S[0]; //0111  
    assign #0.1 P[8] =  S[3] && ~S[2] && ~S[1] && ~S[0]; //1000
    assign #0.1 P[9] =  S[3] && ~S[2] && ~S[1] &&  S[0]; //1001
    assign #0.1 P[19] = S[3] && ~S[2] &&  S[1] && ~S[0]; //1010
    //下面的是代表什么情况下有分支的情况下
    assign #0.1 P[10] = ~Op[5] && ~Op[4] && ~Op[3] && ~Op[2] &&  Op[1] && ~Op[0] && ~S[3] && ~S[2] && ~S[1] &&  S[0]; //000010 0001 -> j 0001
    assign #0.1 P[11] = ~Op[5] && ~Op[4] && ~Op[3] &&  Op[2] && ~Op[1] && ~Op[0] && ~S[3] && ~S[2] && ~S[1] &&  S[0]; //000100 0001 -> beq 0001
    assign #0.1 P[12] = ~Op[5] && ~Op[4] && ~Op[3] && ~Op[2] && ~Op[1] && ~Op[0] && ~S[3] && ~S[2] && ~S[1] &&  S[0]; //000000 0001 ->R_type 0001
    assign #0.1 P[13] =  Op[5] && ~Op[4] && ~Op[3] && ~Op[2] &&  Op[1] &&  Op[0] && ~S[3] && ~S[2] &&  S[1] && ~S[0]; //100011 0010 ->lw 0010
    assign #0.1 P[14] =  Op[5] && ~Op[4] &&  Op[3] && ~Op[2] &&  Op[1] &&  Op[0] && ~S[3] && ~S[2] && ~S[1] &&  S[0]; //101011 0001 ->sw 0001
    assign #0.1 P[15] =  Op[5] && ~Op[4] && ~Op[3] && ~Op[2] &&  Op[1] &&  Op[0] && ~S[3] && ~S[2] && ~S[1] &&  S[0]; //100011 0001 ->lw 0001
    assign #0.1 P[16] =  Op[5] && ~Op[4] &&  Op[3] && ~Op[2] &&  Op[1] &&  Op[0] && ~S[3] && ~S[2] &&  S[1] && ~S[0]; //101011 0010 ->sw 0010
    //addiu指令新增的
    assign #0.1 P[17] = ~Op[5] && ~Op[4] &&  Op[3] && ~Op[2] && ~Op[1] &&  Op[0] && ~S[3] && ~S[2] && ~S[1] &&  S[0]; //001001 0001 ->addiu 0001
    assign #0.1 P[18] = ~Op[5] && ~Op[4] &&  Op[3] && ~Op[2] && ~Op[1] &&  Op[0] && ~S[3] && ~S[2] &&  S[1] && ~S[0]; //001001 0010 ->addiu 0010

    //组合逻辑下方或门
    assign #0.1 PCWr = P[0] || P[9];
    assign #0.1 PCWrCond = P[8];
    assign #0.1 IorD = P[3] || P[5];
    assign #0.1 MemRd = P[0] || P[3];
    assign #0.1 MemWr =P[5];
    assign #0.1 IRWr = P[0];
    assign #0.1 MemtoReg = P[4];
    assign #0.1 PCSrc = {P[9],P[8]};
    assign #0.1 ALUOp = {P[6],P[8]};
    assign #0.1 ALUSrcB = {P[1]||P[2],P[0]||P[1]};
    assign #0.1 ALUSrcA = P[2] || P[6] || P[8];
    //assign #0.1 RegWr = P[4] || P[7];
    assign #0.1 RegWr = P[4] || P[7] || P[19];
    assign #0.1 RegDst = P[7];
    // assign #0.1 NS[3] = P[10] || P[11];
    // assign #0.1 NS[2] = P[3] || P[6] || P[12] || P[16];
    // assign #0.1 NS[1] = P[6] || P[12] || P[13] || P[14] || P[15];
    // assign #0.1 NS[0] = P[0] || P[6] || P[10] || P[13] || P[16];
    assign #0.1 NS[3] = P[10] || P[11] || P[18];
    assign #0.1 NS[2] = P[3] || P[6] || P[12] || P[16];
    assign #0.1 NS[1] = P[6] || P[12] || P[13] || P[14] || P[15] || P[17] || P[18];
    assign #0.1 NS[0] = P[0] || P[6] || P[10] || P[13] || P[16];


    always @(posedge clk) begin
        #0.1
        S <= NS;
    end

endmodule

单周期多周期CPU设计/Multi Cycle Processor/include/CPU_logic.v
// `include "ALU_Ctrl.v"
// `include "ALU.v"
// `include "CU_logic.v"
// `include "Mem.v"
// `include "mux2.v"
// `include "mux4.v"
// `include "Reg.v"
// `include "RF.v"
// `include "SigExt.v"

module CPU_logic(clk);
input clk;

//控制信号线
wire PCWr,PCWrCond,IorD,MemRd,MemWr,IRWr,MemtoReg,ALUSrcA,RegWr,RegDst;
wire [1:0] PCSrc;
wire [1:0] ALUOp;
wire [1:0] ALUSrcB;
wire [2:0] ALUCtrl;
wire Zero,O;

wire [31:0] Inst;//指令线，紫色的
wire [31:0] PC_out;//PC线，蓝色的
wire [31:0] PC_in;
wire [31:0] ALU_a;//ALU线和ALU_Out的输出线，绿色的
wire [31:0] ALU_b;
wire [31:0] ALU_c;
wire [31:0] ALU_Out_out;
wire [31:0] mem_addr;//存储器mem相关连线
wire [31:0] mem_rd;
wire [31:0] mem_wd;
wire [31:0] SigExt_out;//移位器输出线,黄色
wire [31:0] MDR_out;//MDR输出线，黄色
wire [31:0] A_out;//A的输出线，黄色
wire [31:0] RF_data1;//RF有关的线，墨绿色
wire [31:0] RF_data2;
wire [31:0] RF_W_data;
wire [4:0] RF_W_Reg;

//控制器
CU_logic CU(.PCWr(PCWr), .PCWrCond(PCWrCond), .IorD(IorD), .MemRd(MemRd), .MemWr(MemWr), .IRWr(IRWr), .MemtoReg(MemtoReg), .PCSrc(PCSrc), .ALUOp(ALUOp), .ALUSrcB(ALUSrcB), .ALUSrcA(ALUSrcA), .RegWr(RegWr), .RegDst(RegDst), .Op(Inst[31:26]), .clk(clk));
ALU_Ctrl alu_ctrl(.ALUOp(ALUOp), .func(Inst[5:0]), .ALUCtrl(ALUCtrl));

//运算器
ALU alu(.ALU_a(ALU_a), .ALU_b(ALU_b), .ALUCtrl(ALUCtrl), .Zero(Zero), .O(O), .ALU_c(ALU_c));

//存储器
Mem mem(.R_data(mem_rd), .W_data(mem_wd), .Addr(mem_addr), .MemWr(MemWr), .MemRd(MemRd));

//寄存器堆
RF RegFile(.R_Reg1(Inst[25:21]), .R_Reg2(Inst[20:16]), .W_Reg(RF_W_Reg), .W_data(RF_W_data), .R_data1(RF_data1), .R_data2(RF_data2), .clk(clk), .RegWr(RegWr));

//寄存器
Reg PC(.clk(clk), .data(PC_in), .Wr(PCWr||(PCWrCond&&Zero)), .Q(PC_out));
Reg IR(.clk(clk), .data(mem_rd), .Wr(IRWr), .Q(Inst));
Reg MDR(.clk(clk), .data(mem_rd), .Wr(1'b1), .Q(MDR_out));
Reg A(.clk(clk), .data(RF_data1), .Wr(1'b1), .Q(A_out));
Reg B(.clk(clk), .data(RF_data2), .Wr(1'b1), .Q(mem_wd));
Reg ALU_Out(.clk(clk), .data(ALU_c), .Wr(1'b1), .Q(ALU_Out_out));

//多路选择器
mux2 mux2_1(.in0(PC_out), .in1(ALU_Out_out), .out(mem_addr), .addr(IorD));
mux2 mux2_2(.in0(ALU_Out_out), .in1(MDR_out), .out(RF_W_data), .addr(MemtoReg));
mux2 #(4) mux2_3(.in0(Inst[20:16]), .in1(Inst[15:11]), .out(RF_W_Reg), .addr(RegDst));
mux2 mux2_4(.in0(PC_out), .in1(A_out), .out(ALU_a), .addr(ALUSrcA));
mux4 mux4_1(.in0(mem_wd), .in1(32'h00000004), .in2(SigExt_out), .in3(SigExt_out<<2), .out(ALU_b), .addr(ALUSrcB));
mux4 mux4_2(.in0(ALU_c), .in1(ALU_Out_out), .in2({PC_out[31:28],Inst[25:0],2'b00}), .in3(32'hzzzzzzzz), .out(PC_in), .addr(PCSrc));

//移位器
SigExt sigext (.in(Inst[15:0]), .out(SigExt_out));

endmodule

单周期多周期CPU设计/Multi Cycle Processor/testbench/CPU_logic_lw_tb.v
`timescale 10ns/1ns
`include "../include/ALU_Ctrl.v"
`include "../include/ALU.v"
`include "../include/CU_logic.v"
`include "../include/Mem.v"
`include "../include/mux2.v"
`include "../include/mux4.v"
`include "../include/Reg.v"
`include "../include/RF.v"
`include "../include/SigExt.v"
`include "../include/CPU_logic.v"

module CPU_logic_lw_tb;
    //指令存储在32'b00000000-32'b00000003的位置
    //数据在32'b00000004--32'b00000007的位置
    //指令内容为 lW $4,(32'h2)($1),
    //即把寄存器1的内容+32'h2作为addr（结果为00000004）
    //取出数赋值给寄存器4
    //对应的机器码为 100011 00001 00100 0000000000000010
    reg clk;
    parameter clk_period = 10;

    initial begin
        $dumpfile("../vcd/CPU_logic_lw_tb.vcd");             
        $dumpvars(0, CPU_logic_lw_tb); 
        $readmemh("../file/lw_RF.txt",cpu.RegFile.RF);//设置RF初值
        $readmemh("../file/lw.txt",cpu.mem.data);//设置存储器初值
        
        clk <= 1 ;
        #0.2 cpu.PC.Q <= 32'h0; //pc赋值
        cpu.CU.S <= 4'b0000;

        #6000 $finish; 
    end

    always #(clk_period/2) clk = ~clk;

    CPU_logic cpu(.clk(clk));

endmodule

单周期多周期CPU设计/Multi Cycle Processor/vcd/CPU_logic_lw_tb.vcd
$date
	Fri Jan 27 13:21:59 2023
$end
$version
	Icarus Verilog
$end
$timescale
	1ns
$end
$scope module CPU_logic_lw_tb $end
$var parameter 32 ! clk_period $end
$var reg 1 " clk $end
$scope module cpu $end
$var wire 1 " clk $end
$var wire 32 # mem_wd [31:0] $end
$var wire 32 $ mem_rd [31:0] $end
$var wire 32 % mem_addr [31:0] $end
$var wire 1 & Zero $end
$var wire 32 ' SigExt_out [31:0] $end
$var wire 1 ( RegWr $end
$var wire 1 ) RegDst $end
$var wire 32 * RF_data2 [31:0] $end
$var wire 32 + RF_data1 [31:0] $end
$var wire 32 , RF_W_data [31:0] $end
$var wire 5 - RF_W_Reg [4:0] $end
$var wire 32 . PC_out [31:0] $end
$var wire 32 / PC_in [31:0] $end
$var wire 1 0 PCWrCond $end
$var wire 1 1 PCWr $end
$var wire 2 2 PCSrc [1:0] $end
$var wire 1 3 O $end
$var wire 1 4 MemtoReg $end
$var wire 1 5 MemWr $end
$var wire 1 6 MemRd $end
$var wire 32 7 MDR_out [31:0] $end
$var wire 1 8 IorD $end
$var wire 32 9 Inst [31:0] $end
$var wire 1 : IRWr $end
$var wire 32 ; A_out [31:0] $end
$var wire 32 < ALU_c [31:0] $end
$var wire 32 = ALU_b [31:0] $end
$var wire 32 > ALU_a [31:0] $end
$var wire 32 ? ALU_Out_out [31:0] $end
$var wire 2 @ ALUSrcB [1:0] $end
$var wire 1 A ALUSrcA $end
$var wire 2 B ALUOp [1:0] $end
$var wire 3 C ALUCtrl [2:0] $end
$scope module A $end
$var wire 1 D Wr $end
$var wire 1 " clk $end
$var wire 32 E data [31:0] $end
$var reg 32 F Q [31:0] $end
$upscope $end
$scope module ALU_Out $end
$var wire 1 G Wr $end
$var wire 1 " clk $end
$var wire 32 H data [31:0] $end
$var reg 32 I Q [31:0] $end
$upscope $end
$scope module B $end
$var wire 1 J Wr $end
$var wire 1 " clk $end
$var wire 32 K data [31:0] $end
$var reg 32 L Q [31:0] $end
$upscope $end
$scope module CU $end
$var wire 1 A ALUSrcA $end
$var wire 1 8 IorD $end
$var wire 1 6 MemRd $end
$var wire 6 M Op [5:0] $end
$var wire 1 1 PCWr $end
$var wire 1 ( RegWr $end
$var wire 1 " clk $end
$var wire 1 ) RegDst $end
$var wire 1 0 PCWrCond $end
$var wire 2 N PCSrc [1:0] $end
$var wire 20 O P [19:0] $end
$var wire 4 P NS [3:0] $end
$var wire 1 4 MemtoReg $end
$var wire 1 5 MemWr $end
$var wire 1 : IRWr $end
$var wire 2 Q ALUSrcB [1:0] $end
$var wire 2 R ALUOp [1:0] $end
$var reg 4 S S [3:0] $end
$upscope $end
$scope module IR $end
$var wire 1 : Wr $end
$var wire 1 " clk $end
$var wire 32 T data [31:0] $end
$var reg 32 U Q [31:0] $end
$upscope $end
$scope module MDR $end
$var wire 1 V Wr $end
$var wire 1 " clk $end
$var wire 32 W data [31:0] $end
$var reg 32 X Q [31:0] $end
$upscope $end
$scope module PC $end
$var wire 1 Y Wr $end
$var wire 1 " clk $end
$var wire 32 Z data [31:0] $end
$var reg 32 [ Q [31:0] $end
$upscope $end
$scope module RegFile $end
$var wire 5 \ R_Reg1 [4:0] $end
$var wire 5 ] R_Reg2 [4:0] $end
$var wire 32 ^ R_data1 [31:0] $end
$var wire 32 _ R_data2 [31:0] $end
$var wire 1 ( RegWr $end
$var wire 1 " clk $end
$var wire 32 ` W_data [31:0] $end
$var wire 5 a W_Reg [4:0] $end
$upscope $end
$scope module alu $end
$var wire 32 b ALU_b [31:0] $end
$var wire 32 c ALU_a [31:0] $end
$var wire 3 d ALUCtrl [2:0] $end
$var parameter 3 e ADD $end
$var parameter 3 f ADDU $end
$var parameter 32 g ALU_pause $end
$var parameter 3 h AND $end
$var parameter 3 i NOR $end
$var parameter 3 j OR $end
$var parameter 3 k SUB $end
$var reg 32 l ALU_c [31:0] $end
$var reg 1 3 O $end
$var reg 1 & Zero $end
$upscope $end
$scope module alu_ctrl $end
$var wire 2 m ALUOp [1:0] $end
$var wire 6 n func [5:0] $end
$var reg 3 o ALUCtrl [2:0] $end
$upscope $end
$scope module mem $end
$var wire 1 6 MemRd $end
$var wire 1 5 MemWr $end
$var wire 32 p W_data [31:0] $end
$var wire 32 q R_data [31:0] $end
$var wire 32 r Addr [31:0] $end
$upscope $end
$scope module mux2_1 $end
$var wire 1 8 addr $end
$var wire 32 s in0 [31:0] $end
$var wire 32 t in1 [31:0] $end
$var wire 32 u out [31:0] $end
$var parameter 32 v width $end
$upscope $end
$scope module mux2_2 $end
$var wire 1 4 addr $end
$var wire 32 w in0 [31:0] $end
$var wire 32 x in1 [31:0] $end
$var wire 32 y out [31:0] $end
$var parameter 32 z width $end
$upscope $end
$scope module mux2_3 $end
$var wire 1 ) addr $end
$var wire 5 { in0 [4:0] $end
$var wire 5 | in1 [4:0] $end
$var wire 5 } out [4:0] $end
$var parameter 32 ~ width $end
$upscope $end
$scope module mux2_4 $end
$var wire 1 A addr $end
$var wire 32 !" in0 [31:0] $end
$var wire 32 "" in1 [31:0] $end
$var wire 32 #" out [31:0] $end
$var parameter 32 $" width $end
$upscope $end
$scope module mux4_1 $end
$var wire 2 %" addr [1:0] $end
$var wire 32 &" in0 [31:0] $end
$var wire 32 '" in1 [31:0] $end
$var wire 32 (" in3 [31:0] $end
$var wire 32 )" in2 [31:0] $end
$var parameter 32 *" width $end
$var reg 32 +" out [31:0] $end
$upscope $end
$scope module mux4_2 $end
$var wire 2 ," addr [1:0] $end
$var wire 32 -" in0 [31:0] $end
$var wire 32 ." in1 [31:0] $end
$var wire 32 /" in2 [31:0] $end
$var wire 32 0" in3 [31:0] $end
$var parameter 32 1" width $end
$var reg 32 2" out [31:0] $end
$upscope $end
$scope module sigext $end
$var wire 16 3" in [15:0] $end
$var wire 32 4" out [31:0] $end
$upscope $end
$upscope $end
$upscope $end
$enddefinitions $end
$comment Show the parameter values. $end
$dumpall
b11111 1"
b11111 *"
b11111 $"
b100 ~
b11111 z
b11111 v
b110 k
b1 j
b11 i
b0 h
b0 g
b101 f
b100 e
b1010 !
$end
#0
$dumpvars
bx 4"
bx 3"
bx 2"
bz 0"
bx00 /"
bx ."
bx -"
bx ,"
bx +"
bx )"
bx00 ("
b100 '"
bx &"
bx %"
bx #"
bx ""
bx !"
bx }
bx |
bx {
bx y
bx x
bx w
bx u
bx t
bx s
bx r
bx q
bx p
bx o
bx n
bx m
bx l
bx d
bx c
bx b
bx a
bx `
bx _
bx ^
bx ]
bx \
bx [
bx Z
xY
bx X
bx W
1V
bx U
bx T
bx S
bx R
bx Q
bx P
bx O
bx N
bx M
bx L
bx K
1J
bx I
bx H
1G
bx F
bx E
1D
bx C
bx B
xA
bx @
bx ?
bx >
bx =
bx <
bx ;
x:
bx 9
x8
bx 7
x6
x5
x4
x3
bx 2
x1
x0
bx /
bx .
bx -
bx ,
bx +
bx *
x)
x(
bx '
x&
bx %
bx $
bx #
1"
$end
#2
b0xxxxxxxxxxxxxxxxxxxxxxxxxx00 /"
b0 S
b0 .
b0 [
b0 s
b0 !"
#3
b1 O
#4
1Y
0A
0(
b1 P
b1 @
b1 Q
b1 %"
16
08
11
1:
04
00
b0 B
b0 R
b0 m
05
0)
b0 2
b0 N
b0 ,"
#5
b100 =
b100 b
b100 +"
b100 C
b100 d
b100 o
b0 >
b0 c
b0 #"
b0 %
b0 r
b0 u
#6
0&
03
b100 <
b100 H
b100 l
b100 -"
#7
b100 /
b100 Z
b100 2"
#15
b10001100001001000000000000000010 $
b10001100001001000000000000000010 T
b10001100001001000000000000000010 W
b10001100001001000000000000000010 q
#50
0"
#100
1"
#101
b10 3"
b100100000000000000001000 /"
b0 |
b100 {
b100 ]
b1 \
b10 n
b100011 M
b100 ?
b100 I
b100 t
b100 w
b100 ."
b10001100001001000000000000000010 7
b10001100001001000000000000000010 X
b10001100001001000000000000000010 x
b10001100001001000000000000000010 9
b10001100001001000000000000000010 U
b100 .
b100 [
b100 s
b100 !"
b1 S
#102
b1000 ("
b100 -
b100 a
b100 }
b1000000000000010 O
b100 ,
b100 `
b100 y
b10 '
b10 )"
b10 4"
b11011100000000010000000000011110 *
b11011100000000010000000000011110 K
b11011100000000010000000000011110 _
b10 +
b10 E
b10 ^
b100 %
b100 r
b100 u
b100 >
b100 c
b100 #"
#103
b1000 <
b1000 H
b1000 l
b1000 -"
0Y
b10 P
01
06
b11 @
b11 Q
b11 %"
0:
#104
b1000 /
b1000 Z
b1000 2"
b1000 =
b1000 b
b1000 +"
#105
b1100 <
b1100 H
b1100 l
b1100 -"
#106
b1100 /
b1100 Z
b1100 2"
#113
bz $
bz T
bz W
bz q
#150
0"
#200
1"
#201
b10 S
bz 7
bz X
bz x
b10 ;
b10 F
b10 ""
b11011100000000010000000000011110 #
b11011100000000010000000000011110 L
b11011100000000010000000000011110 p
b11011100000000010000000000011110 &"
b1100 ?
b1100 I
b1100 t
b1100 w
b1100 ."
#202
b10000000000100 O
b1100 ,
b1100 `
b1100 y
#203
1A
b11 P
b10 @
b10 Q
b10 %"
#204
b10 =
b10 b
b10 +"
b10 >
b10 c
b10 #"
#205
b100 <
b100 H
b100 l
b100 -"
#206
b100 /
b100 Z
b100 2"
#250
0"
#300
1"
#301
b100 ?
b100 I
b100 t
b100 w
b100 ."
b11 S
#302
b1000 O
b100 ,
b100 `
b100 y
#303
0A
b100 P
b0 @
b0 Q
b0 %"
18
16
#304
b11011100000000010000000000011110 =
b11011100000000010000000000011110 b
b11011100000000010000000000011110 +"
b100 >
b100 c
b100 #"
#305
b11011100000000010000000000100010 <
b11011100000000010000000000100010 H
b11011100000000010000000000100010 l
b11011100000000010000000000100010 -"
#306
b11011100000000010000000000100010 /
b11011100000000010000000000100010 Z
b11011100000000010000000000100010 2"
#313
b11100000111111010000000100110010 $
b11100000111111010000000100110010 T
b11100000111111010000000100110010 W
b11100000111111010000000100110010 q
#350
0"
#400
1"
#401
b100 S
b11100000111111010000000100110010 7
b11100000111111010000000100110010 X
b11100000111111010000000100110010 x
b11011100000000010000000000100010 ?
b11011100000000010000000000100010 I
b11011100000000010000000000100010 t
b11011100000000010000000000100010 w
b11011100000000010000000000100010 ."
#402
b10000 O
b11011100000000010000000000100010 %
b11011100000000010000000000100010 r
b11011100000000010000000000100010 u
b11011100000000010000000000100010 ,
b11011100000000010000000000100010 `
b11011100000000010000000000100010 y
#403
b0 P
1(
08
06
14
#404
b100 %
b100 r
b100 u
b11100000111111010000000100110010 ,
b11100000111111010000000100110010 `
b11100000111111010000000100110010 y
#413
bz $
bz T
bz W
bz q
#450
0"
#500
1"
#501
bz 7
bz X
bz x
b0 S
#502
b1 O
bz ,
bz `
bz y
b11100000111111010000000100110010 *
b11100000111111010000000100110010 K
b11100000111111010000000100110010 _
#503
1Y
b1 P
0(
11
16
b1 @
b1 Q
b1 %"
1:
04
#504
b100 =
b100 b
b100 +"
b11011100000000010000000000100010 ,
b11011100000000010000000000100010 `
b11011100000000010000000000100010 y
#505
b1000 <
b1000 H
b1000 l
b1000 -"
#506
b1000 /
b1000 Z
b1000 2"
#513
b11100000111111010000000100110010 $
b11100000111111010000000100110010 T
b11100000111111010000000100110010 W
b11100000111111010000000100110010 q
#550
0"
#600
1"
#601
b100110010 3"
b11111101000000010011001000 /"
b11101 {
b11101 ]
b111 \
b110010 n
b111000 M
b1 S
b1000 .
b1000 [
b1000 s
b1000 !"
b11100000111111010000000100110010 9
b11100000111111010000000100110010 U
b11100000111111010000000100110010 7
b11100000111111010000000100110010 X
b11100000111111010000000100110010 x
b11100000111111010000000100110010 #
b11100000111111010000000100110010 L
b11100000111111010000000100110010 p
b11100000111111010000000100110010 &"
b1000 ?
b1000 I
b1000 t
b1000 w
b1000 ."
#602
b10011001000 ("
b10 O
b11101 -
b11101 a
b11101 }
b1000 %
b1000 r
b1000 u
b1000 >
b1000 c
b1000 #"
b100110010 '
b100110010 )"
b100110010 4"
bx *
bx K
bx _
bx +
bx E
bx ^
b1000 ,
b1000 `
b1000 y
#603
b1100 <
b1100 H
b1100 l
b1100 -"
0Y
b0 P
01
06
b11 @
b11 Q
b11 %"
0:
#604
b1100 /
b1100 Z
b1100 2"
b10011001000 =
b10011001000 b
b10011001000 +"
#605
b10011010000 <
b10011010000 H
b10011010000 l
b10011010000 -"
#606
b10011010000 /
b10011010000 Z
b10011010000 2"
#613
bz $
bz T
bz W
bz q
#650
0"
#700
1"
#701
b10011010000 ?
b10011010000 I
b10011010000 t
b10011010000 w
b10011010000 ."
bx #
bx L
bx p
bx &"
bx ;
bx F
bx ""
bz 7
bz X
bz x
b0 S
#702
b1 O
b10011010000 ,
b10011010000 `
b10011010000 y
#703
1Y
b1 P
11
16
b1 @
b1 Q
b1 %"
1:
#704
b100 =
b100 b
b100 +"
#705
b1100 <
b1100 H
b1100 l
b1100 -"
#706
b1100 /
b1100 Z
b1100 2"
#713
bx $
bx T
bx W
bx q
#750
0"
#800
1"
#801
bx 3"
b0xxxxxxxxxxxxxxxxxxxxxxxxxx00 /"
bx |
bx {
bx ]
bx \
bx n
bx M
b1 S
b1100 .
b1100 [
b1100 s
b1100 !"
bx 9
bx U
bx 7
bx X
bx x
b1100 ?
b1100 I
b1100 t
b1100 w
b1100 ."
#802
bx00 ("
b0x0xx0xxx0000000010 O
bx -
bx a
bx }
b1100 %
b1100 r
b1100 u
b1100 >
b1100 c
b1100 #"
bx '
bx )"
bx 4"
b1100 ,
b1100 `
b1100 y
#803
b10000 <
b10000 H
b10000 l
b10000 -"
0Y
bx P
01
06
b11 @
b11 Q
b11 %"
0:
#804
b10000 /
b10000 Z
b10000 2"
bx00 =
bx00 b
bx00 +"
#805
x3
bx <
bx H
bx l
bx -"
#806
bx /
bx Z
bx 2"
#813
bz $
bz T
bz W
bz q
#850
0"
#900
1"
#901
bx ?
bx I
bx t
bx w
bx ."
bz 7
bz X
bz x
bx S
#902
bx O
bx ,
bx `
bx y
#903
xY
xA
x(
x1
x8
x6
bx @
bx Q
bx %"
x4
x5
x)
x0
bx B
bx R
bx m
bx 2
bx N
bx ,"
x:
#904
bx >
bx c
bx #"
bx %
bx r
bx u
#913
bx $
bx T
bx W
bx q
#950
0"
#1000
1"
#1001
bx 7
bx X
bx x
